[{"date":"2022-03-14","black":"Cao Zhenyu","blackElo":2984,"white":"Wang Zeyu","whiteElo":3012,"result":"0-1","delta":"-18.3"},{"date":"2021-08-31","black":"Cao Zhenyu","blackElo":3001,"white":"Hu Xiao","whiteElo":3043,"result":"0-1","delta":"-17.6"},{"date":"2021-08-27","black":"Cao Zhenyu","blackElo":2980,"white":"Li Chengze","whiteElo":3000,"result":"1-0","delta":"+21.2"},{"date":"2021-04-12","black":"Wang Chuxuan","blackElo":3000,"white":"Cao Zhenyu","whiteElo":3000,"result":"1-0","delta":"-20.0"}]
