[{"date":"2025-08-31","black":"Fan Yin","blackElo":3405,"white":"Huang Yunsong","whiteElo":3282,"result":"0-1","delta":"-13.4"},{"date":"2025-08-29","black":"Huang Yunsong","blackElo":3289,"white":"Fan Yin","whiteElo":3398,"result":"0-1","delta":"+6.9"},{"date":"2025-08-27","black":"Chen Haoxin","blackElo":3188,"white":"Fan Yin","whiteElo":3393,"result":"0-1","delta":"+4.7"},{"date":"2025-07-22","black":"Fan Yin","blackElo":3390,"white":"Zhou Ziyi","whiteElo":3138,"result":"1-0","delta":"+3.8"},{"date":"2025-07-19","black":"Tu Xiaoyu","blackElo":3418,"white":"Fan Yin","whiteElo":3379,"result":"0-1","delta":"+11.1"},{"date":"2025-07-02","black":"Xie Erhao","blackElo":3358,"white":"Fan Yin","whiteElo":3369,"result":"0-1","delta":"+9.7"},{"date":"2025-07-01","black":"Fan Yin","blackElo":3368,"white":"Andrii Kravets","whiteElo":2843,"result":"1-0","delta":"+0.9"},{"date":"2025-06-29","black":"Fan Yin","blackElo":3359,"white":"Wang Yuanjun","whiteElo":3319,"result":"1-0","delta":"+8.9"},{"date":"2025-06-17","black":"Fan Yin","blackElo":3367,"white":"Xie Ke","whiteElo":3443,"result":"0-1","delta":"-7.8"},{"date":"2025-06-15","black":"Fan Yin","blackElo":3361,"white":"Xu Yidi","whiteElo":3231,"result":"1-0","delta":"+6.4"},{"date":"2025-05-29","black":"Fan Yin","blackElo":3346,"white":"Ke Jie","whiteElo":3502,"result":"1-0","delta":"+14.2"},{"date":"2025-05-27","black":"Wang Chunhui","blackElo":3232,"white":"Fan Yin","whiteElo":3339,"result":"0-1","delta":"+7.0"},{"date":"2025-05-12","black":"Tu Xiaoyu","blackElo":3465,"white":"Fan Yin","whiteElo":3346,"result":"1-0","delta":"-6.7"},{"date":"2025-05-11","black":"Fan Yin","blackElo":3343,"white":"Liu Qifeng","whiteElo":3068,"result":"1-0","delta":"+3.4"},{"date":"2025-04-23","black":"Fan Yin","blackElo":3334,"white":"Sim Jaeik","whiteElo":3287,"result":"1-0","delta":"+8.7"},{"date":"2025-04-22","black":"Fan Yin","blackElo":3324,"white":"Seol Hyunjun","whiteElo":3335,"result":"1-0","delta":"+10.3"},{"date":"2025-04-03","black":"Shin Jinseo","blackElo":3731,"white":"Fan Yin","whiteElo":3325,"result":"1-0","delta":"-1.8"},{"date":"2025-03-13","black":"Fan Yin","blackElo":3317,"white":"Na Hyun","whiteElo":3251,"result":"1-0","delta":"+8.1"},{"date":"2025-03-06","black":"Park Junghwan","blackElo":3537,"white":"Fan Yin","whiteElo":3301,"result":"0-1","delta":"+15.9"},{"date":"2025-03-03","black":"Wang Xinghao","blackElo":3548,"white":"Fan Yin","whiteElo":3305,"result":"1-0","delta":"-4.0"},{"date":"2025-01-19","black":"Fan Yin","blackElo":3314,"white":"Kim Junghyun","whiteElo":3348,"result":"0-1","delta":"-9.0"},{"date":"2024-12-30","black":"Fan Yin","blackElo":3307,"white":"Li Haotong","whiteElo":3214,"result":"1-0","delta":"+7.4"},{"date":"2024-12-28","black":"Fan Yin","blackElo":3315,"white":"Lee Changseok","whiteElo":3373,"result":"0-1","delta":"-8.4"},{"date":"2024-12-21","black":"Park Minkyu","blackElo":3253,"white":"Fan Yin","whiteElo":3327,"result":"1-0","delta":"-12.1"},{"date":"2024-12-14","black":"Xu Haohong","blackElo":3528,"white":"Fan Yin","whiteElo":3332,"result":"1-0","delta":"-4.9"},{"date":"2024-11-15","black":"Fan Yin","blackElo":3337,"white":"Li Xuanhao","whiteElo":3528,"result":"0-1","delta":"-5.0"},{"date":"2024-11-12","black":"Pongsakarn Sornarra Ama.","blackElo":2952,"white":"Fan Yin","whiteElo":3335,"result":"0-1","delta":"+2.0"},{"date":"2024-11-08","black":"Liu Yuhang","blackElo":3390,"white":"Fan Yin","whiteElo":3344,"result":"1-0","delta":"-8.7"},{"date":"2024-10-18","black":"Fan Yin","blackElo":3336,"white":"Wang Shiyi","whiteElo":3270,"result":"1-0","delta":"+8.1"},{"date":"2024-10-09","black":"Shi Yue","blackElo":3367,"white":"Fan Yin","whiteElo":3345,"result":"1-0","delta":"-9.4"},{"date":"2024-09-19","black":"Xie Ke","blackElo":3411,"white":"Fan Yin","whiteElo":3354,"result":"1-0","delta":"-8.4"},{"date":"2024-09-15","black":"Fan Tingyu","blackElo":3485,"white":"Fan Yin","whiteElo":3360,"result":"1-0","delta":"-6.6"},{"date":"2024-09-03","black":"Fan Yin","blackElo":3374,"white":"Xia Chenkun","whiteElo":3241,"result":"0-1","delta":"-13.6"},{"date":"2024-08-24","black":"Fan Yin","blackElo":3371,"white":"Ma Jingyuan","whiteElo":3067,"result":"1-0","delta":"+3.0"},{"date":"2024-08-16","black":"Fan Yin","blackElo":3362,"white":"Jiang Qirun","whiteElo":3313,"result":"1-0","delta":"+8.6"},{"date":"2024-08-10","black":"Liu Zhaozhe","blackElo":3141,"white":"Fan Yin","whiteElo":3358,"result":"0-1","delta":"+4.5"},{"date":"2024-07-23","black":"Fan Yin","blackElo":3371,"white":"Han Yizhou","whiteElo":3253,"result":"0-1","delta":"-13.3"},{"date":"2024-06-23","black":"Zhou Ziyi","blackElo":3201,"white":"Fan Yin","whiteElo":3366,"result":"0-1","delta":"+5.6"},{"date":"2024-06-19","black":"Mi Yuting","blackElo":3388,"white":"Fan Yin","whiteElo":3375,"result":"1-0","delta":"-9.6"},{"date":"2024-06-16","black":"Fan Yin","blackElo":3383,"white":"Lian Xiao","whiteElo":3464,"result":"0-1","delta":"-7.7"},{"date":"2024-06-14","black":"Fan Yin","blackElo":3368,"white":"Li Xuanhao","whiteElo":3535,"result":"1-0","delta":"+14.5"},{"date":"2024-06-13","black":"Fan Yin","blackElo":3359,"white":"Chen Xian","whiteElo":3337,"result":"1-0","delta":"+9.4"},{"date":"2024-06-12","black":"Fan Yin","blackElo":3347,"white":"Xu Jiayang","whiteElo":3434,"result":"1-0","delta":"+12.5"},{"date":"2024-06-10","black":"Fan Yin","blackElo":3335,"white":"Seol Hyunjun","whiteElo":3378,"result":"1-0","delta":"+11.2"},{"date":"2024-06-03","black":"Chen Zijian","blackElo":3353,"white":"Fan Yin","whiteElo":3345,"result":"1-0","delta":"-9.8"},{"date":"2024-05-29","black":"Fan Yin","blackElo":3330,"white":"Yang Dingxin","whiteElo":3518,"result":"1-0","delta":"+14.9"},{"date":"2024-05-27","black":"Zeng Yuanhai","blackElo":3003,"white":"Fan Yin","whiteElo":3327,"result":"0-1","delta":"+2.7"},{"date":"2024-04-01","black":"Fan Yin","blackElo":3337,"white":"Tuo Jiaxi","whiteElo":3354,"result":"0-1","delta":"-9.5"},{"date":"2024-03-17","black":"Fan Yin","blackElo":3350,"white":"Gu Lingyi","whiteElo":3239,"result":"0-1","delta":"-13.1"},{"date":"2024-03-15","black":"Zhang Ziliang","blackElo":3136,"white":"Fan Yin","whiteElo":3345,"result":"0-1","delta":"+4.6"},{"date":"2024-02-28","black":"Fan Yin","blackElo":3353,"white":"Lian Xiao","whiteElo":3450,"result":"0-1","delta":"-7.3"},{"date":"2024-02-03","black":"Tong Mengcheng","blackElo":3278,"white":"Fan Yin","whiteElo":3365,"result":"1-0","delta":"-12.5"},{"date":"2024-02-01","black":"Fan Yin","blackElo":3353,"white":"Yang Kaiwen","whiteElo":3444,"result":"1-0","delta":"+12.6"},{"date":"2024-01-31","black":"Shi Yue","blackElo":3406,"white":"Fan Yin","whiteElo":3341,"result":"0-1","delta":"+11.9"},{"date":"2024-01-29","black":"Zhao Chenyu","blackElo":3522,"white":"Fan Yin","whiteElo":3326,"result":"0-1","delta":"+15.1"},{"date":"2024-01-26","black":"Fan Yin","blackElo":3331,"white":"Wang Xinghao","whiteElo":3525,"result":"0-1","delta":"-4.9"},{"date":"2024-01-22","black":"Tao Xinran","blackElo":3386,"white":"Fan Yin","whiteElo":3339,"result":"1-0","delta":"-8.7"},{"date":"2024-01-16","black":"Fan Yin","blackElo":3329,"white":"Jiang Weijie","whiteElo":3341,"result":"1-0","delta":"+10.4"},{"date":"2024-01-10","black":"Tuo Jiaxi","blackElo":3411,"white":"Fan Yin","whiteElo":3316,"result":"0-1","delta":"+12.7"},{"date":"2024-01-05","black":"Fan Yin","blackElo":3326,"white":"Lee Changseok","whiteElo":3335,"result":"0-1","delta":"-9.8"},{"date":"2023-12-21","black":"Shin Jinseo","blackElo":3749,"white":"Fan Yin","whiteElo":3307,"result":"0-1","delta":"+18.5"},{"date":"2023-12-06","black":"Fan Yin","blackElo":3321,"white":"Xia Chenkun","whiteElo":3205,"result":"0-1","delta":"-13.2"},{"date":"2023-11-28","black":"Fan Yin","blackElo":3315,"white":"Chen Hao","whiteElo":3138,"result":"1-0","delta":"+5.3"},{"date":"2023-11-13","black":"Fan Yin","blackElo":3321,"white":"Zhao Chenyu","whiteElo":3493,"result":"0-1","delta":"-5.4"},{"date":"2023-11-06","black":"Fan Yin","blackElo":3317,"white":"Chen Yichun","whiteElo":3058,"result":"1-0","delta":"+3.7"},{"date":"2023-10-23","black":"Fan Yin","blackElo":3322,"white":"Ke Jie","whiteElo":3517,"result":"0-1","delta":"-4.9"},{"date":"2023-09-19","black":"Fan Yin","blackElo":3313,"white":"Chen Zijian","whiteElo":3276,"result":"1-0","delta":"+8.9"},{"date":"2023-08-19","black":"Weon Seongjin","blackElo":3395,"white":"Fan Yin","whiteElo":3321,"result":"1-0","delta":"-7.9"},{"date":"2023-08-18","black":"Fan Yin","blackElo":3330,"white":"Liao Yuanhe","whiteElo":3371,"result":"0-1","delta":"-8.8"},{"date":"2023-06-07","black":"Li Weiqing","blackElo":3459,"white":"Fan Yin","whiteElo":3336,"result":"1-0","delta":"-6.6"},{"date":"2023-03-30","black":"Chen Xian","blackElo":3335,"white":"Fan Yin","whiteElo":3347,"result":"1-0","delta":"-10.3"},{"date":"2023-03-29","black":"Fan Yin","blackElo":3339,"white":"Tong Mengcheng","whiteElo":3260,"result":"1-0","delta":"+7.8"},{"date":"2023-03-08","black":"Fan Yin","blackElo":3346,"white":"Fan Tingyu","whiteElo":3451,"result":"0-1","delta":"-7.1"},{"date":"2023-03-07","black":"Peng Quan","blackElo":3162,"white":"Fan Yin","whiteElo":3341,"result":"0-1","delta":"+5.3"},{"date":"2023-02-12","black":"Fan Yin","blackElo":3334,"white":"Xia Chenkun","whiteElo":3220,"result":"1-0","delta":"+6.8"},{"date":"2023-02-11","black":"Fan Yin","blackElo":3319,"white":"Byun Sangil","whiteElo":3494,"result":"1-0","delta":"+14.7"},{"date":"2023-02-07","black":"Byun Sangil","blackElo":3493,"white":"Fan Yin","whiteElo":3325,"result":"1-0","delta":"-5.5"},{"date":"2023-02-06","black":"Fan Yin","blackElo":3335,"white":"Tan Xiao","whiteElo":3345,"result":"0-1","delta":"-9.7"},{"date":"2023-02-05","black":"Zhang Qiang","blackElo":3075,"white":"Fan Yin","whiteElo":3351,"result":"1-0","delta":"-16.6"},{"date":"2023-02-04","black":"Fan Yin","blackElo":3341,"white":"Tang Weixing","whiteElo":3352,"result":"1-0","delta":"+10.3"},{"date":"2023-02-03","black":"Cheng Jiaye","blackElo":3121,"white":"Fan Yin","whiteElo":3336,"result":"0-1","delta":"+4.5"},{"date":"2022-09-27","black":"Fan Yin","blackElo":3345,"white":"Liao Yuanhe","whiteElo":3385,"result":"0-1","delta":"-8.9"},{"date":"2022-09-13","black":"Fan Yin","blackElo":3350,"white":"Ke Jie","whiteElo":3532,"result":"0-1","delta":"-5.2"},{"date":"2022-08-30","black":"Tao Xinran","blackElo":3363,"white":"Fan Yin","whiteElo":3340,"result":"0-1","delta":"+10.7"},{"date":"2022-08-25","black":"Jiang Weijie","blackElo":3357,"white":"Fan Yin","whiteElo":3349,"result":"1-0","delta":"-9.8"},{"date":"2022-08-23","black":"Fan Yin","blackElo":3363,"white":"Cao Xiaoyang","whiteElo":3229,"result":"0-1","delta":"-13.7"},{"date":"2022-08-22","black":"Fan Yin","blackElo":3356,"white":"Chen Yunong","whiteElo":3264,"result":"1-0","delta":"+7.4"},{"date":"2022-08-11","black":"Fan Yin","blackElo":3362,"white":"Fan Tingyu","whiteElo":3505,"result":"0-1","delta":"-6.1"},{"date":"2022-08-10","black":"Fan Yin","blackElo":3355,"white":"Cao Xiaoyang","whiteElo":3230,"result":"1-0","delta":"+6.5"},{"date":"2022-08-09","black":"He Yuhan","blackElo":3143,"white":"Fan Yin","whiteElo":3351,"result":"0-1","delta":"+4.6"},{"date":"2022-08-08","black":"Fan Yin","blackElo":3359,"white":"Wang Xinghao","whiteElo":3425,"result":"0-1","delta":"-8.1"},{"date":"2022-08-06","black":"Kim Jiseok","blackElo":3341,"white":"Fan Yin","whiteElo":3349,"result":"0-1","delta":"+9.8"},{"date":"2022-08-05","black":"Fan Yin","blackElo":3359,"white":"Huang Yunsong","whiteElo":3364,"result":"0-1","delta":"-9.8"},{"date":"2022-08-04","black":"Peng Liyao","blackElo":3392,"white":"Fan Yin","whiteElo":3348,"result":"0-1","delta":"+11.3"},{"date":"2022-08-03","black":"Fan Yin","blackElo":3336,"white":"Lian Xiao","whiteElo":3381,"result":"1-0","delta":"+11.3"},{"date":"2022-04-23","black":"Fan Yin","blackElo":3345,"white":"Xu Jiayang","whiteElo":3378,"result":"0-1","delta":"-9.1"},{"date":"2022-02-18","black":"Fan Yin","blackElo":3354,"white":"Xie Ke","whiteElo":3396,"result":"0-1","delta":"-8.8"},{"date":"2022-02-16","black":"Fan Yin","blackElo":3341,"white":"Yang Dingxin","whiteElo":3460,"result":"1-0","delta":"+13.3"},{"date":"2022-02-14","black":"Yu Zhiying","blackElo":3268,"white":"Fan Yin","whiteElo":3333,"result":"0-1","delta":"+8.2"},{"date":"2022-01-20","black":"Peng Liyao","blackElo":3354,"white":"Fan Yin","whiteElo":3342,"result":"1-0","delta":"-9.7"},{"date":"2022-01-19","black":"Gu Zihao","blackElo":3553,"white":"Fan Yin","whiteElo":3327,"result":"0-1","delta":"+15.7"},{"date":"2022-01-14","black":"Fan Yin","blackElo":3335,"white":"Huang Yunsong","whiteElo":3384,"result":"0-1","delta":"-8.6"},{"date":"2022-01-13","black":"Huang Yunsong","blackElo":3396,"white":"Fan Yin","whiteElo":3323,"result":"0-1","delta":"+12.1"},{"date":"2021-12-25","black":"Rong Yi","blackElo":3263,"white":"Fan Yin","whiteElo":3335,"result":"1-0","delta":"-12.0"},{"date":"2021-12-11","black":"Fan Yin","blackElo":3339,"white":"Ke Jie","whiteElo":3583,"result":"0-1","delta":"-3.9"},{"date":"2021-12-10","black":"Li Xuanhao","blackElo":3376,"white":"Fan Yin","whiteElo":3328,"result":"0-1","delta":"+11.4"},{"date":"2021-11-17","black":"Fan Yin","blackElo":3337,"white":"Li Xuanhao","whiteElo":3367,"result":"0-1","delta":"-9.1"},{"date":"2021-11-15","black":"Meng Tailing","blackElo":3299,"white":"Fan Yin","whiteElo":3328,"result":"0-1","delta":"+9.2"},{"date":"2021-10-09","black":"Fan Yin","blackElo":3315,"white":"Li Qincheng","whiteElo":3415,"result":"1-0","delta":"+12.8"},{"date":"2021-09-30","black":"Fan Yin","blackElo":3302,"white":"Xu Haohong","whiteElo":3416,"result":"1-0","delta":"+13.2"},{"date":"2021-09-29","black":"Fan Yin","blackElo":3312,"white":"Tang Weixing","whiteElo":3320,"result":"0-1","delta":"-9.8"},{"date":"2021-09-28","black":"Shin Minjun","blackElo":3388,"white":"Fan Yin","whiteElo":3299,"result":"0-1","delta":"+12.5"},{"date":"2021-09-26","black":"Fan Yin","blackElo":3308,"white":"Yang Kaiwen","whiteElo":3332,"result":"0-1","delta":"-9.3"},{"date":"2021-09-25","black":"Fan Yin","blackElo":3302,"white":"Zhou Hexi","whiteElo":3166,"result":"1-0","delta":"+6.3"},{"date":"2021-09-03","black":"Fan Yin","blackElo":3313,"white":"Zhang Tao","whiteElo":3269,"result":"0-1","delta":"-11.3"},{"date":"2021-09-02","black":"Xie Ke","blackElo":3421,"white":"Fan Yin","whiteElo":3300,"result":"0-1","delta":"+13.4"},{"date":"2021-08-31","black":"Fan Yin","blackElo":3293,"white":"Jiang Qirun","whiteElo":3196,"result":"1-0","delta":"+7.3"},{"date":"2021-08-27","black":"Fan Yin","blackElo":3282,"white":"Huang Yunsong","whiteElo":3314,"result":"1-0","delta":"+10.9"},{"date":"2021-08-26","black":"Fan Yin","blackElo":3273,"white":"Chen Zijian","whiteElo":3237,"result":"1-0","delta":"+9.0"},{"date":"2021-08-25","black":"Li Xuanhao","blackElo":3359,"white":"Fan Yin","whiteElo":3260,"result":"0-1","delta":"+12.8"},{"date":"2021-08-20","black":"Tong Mengcheng","blackElo":3343,"white":"Fan Yin","whiteElo":3268,"result":"1-0","delta":"-7.9"},{"date":"2021-07-27","black":"Fan Yin","blackElo":3274,"white":"Mi Yuting","whiteElo":3434,"result":"0-1","delta":"-5.7"},{"date":"2021-06-12","black":"Fan Yin","blackElo":3268,"white":"Huang Xin","whiteElo":3095,"result":"1-0","delta":"+5.4"},{"date":"2021-06-11","black":"Zhou Ruiyang","blackElo":3238,"white":"Fan Yin","whiteElo":3279,"result":"1-0","delta":"-11.2"},{"date":"2021-06-07","black":"Chen Hao","blackElo":3139,"white":"Fan Yin","whiteElo":3294,"result":"1-0","delta":"-14.2"},{"date":"2021-05-12","black":"Meng Tailing","blackElo":3282,"white":"Fan Yin","whiteElo":3304,"result":"1-0","delta":"-10.6"},{"date":"2021-05-11","black":"Fan Yin","blackElo":3314,"white":"Zhao Chenyu","whiteElo":3337,"result":"0-1","delta":"-9.3"},{"date":"2021-05-10","black":"Fan Yin","blackElo":3300,"white":"Xie Ke","whiteElo":3443,"result":"1-0","delta":"+13.9"},{"date":"2021-05-08","black":"Tu Xiaoyu","blackElo":3267,"white":"Fan Yin","whiteElo":3290,"result":"0-1","delta":"+9.3"},{"date":"2021-05-07","black":"Lee Donghoon","blackElo":3368,"white":"Fan Yin","whiteElo":3298,"result":"1-0","delta":"-8.0"},{"date":"2021-03-16","black":"Fan Yin","blackElo":3311,"white":"Chen Zijian","whiteElo":3233,"result":"0-1","delta":"-12.2"},{"date":"2021-01-05","black":"Xu Jiayang","blackElo":3399,"white":"Fan Yin","whiteElo":3318,"result":"1-0","delta":"-7.7"},{"date":"2020-12-18","black":"Cao Xiaoyang","blackElo":3258,"white":"Fan Yin","whiteElo":3310,"result":"0-1","delta":"+8.5"},{"date":"2020-12-17","black":"Fan Yin","blackElo":3303,"white":"Liao Xingwen","whiteElo":3173,"result":"1-0","delta":"+6.4"},{"date":"2020-12-16","black":"Fan Yin","blackElo":3313,"white":"Shi Yue","whiteElo":3339,"result":"0-1","delta":"-9.2"},{"date":"2020-12-14","black":"Shi Yue","blackElo":3351,"white":"Fan Yin","whiteElo":3301,"result":"0-1","delta":"+11.4"},{"date":"2020-12-13","black":"Li Qincheng","blackElo":3294,"white":"Fan Yin","whiteElo":3312,"result":"1-0","delta":"-10.5"},{"date":"2020-12-12","black":"Fan Yin","blackElo":3320,"white":"Xu Jiayang","whiteElo":3372,"result":"0-1","delta":"-8.5"},{"date":"2020-12-11","black":"Lee Donghoon","blackElo":3387,"white":"Fan Yin","whiteElo":3308,"result":"0-1","delta":"+12.2"},{"date":"2020-12-09","black":"Fan Yin","blackElo":3300,"white":"Li Chengsen","whiteElo":3210,"result":"1-0","delta":"+7.5"},{"date":"2020-12-08","black":"Zhang Tao","blackElo":3259,"white":"Fan Yin","whiteElo":3312,"result":"1-0","delta":"-11.5"},{"date":"2020-12-07","black":"Shi Yue","blackElo":3335,"white":"Fan Yin","whiteElo":3322,"result":"1-0","delta":"-9.6"},{"date":"2020-12-06","black":"He Yuhan","blackElo":3243,"white":"Fan Yin","whiteElo":3314,"result":"0-1","delta":"+8.0"},{"date":"2020-11-18","black":"Jiang Weijie","blackElo":3431,"white":"Fan Yin","whiteElo":3300,"result":"0-1","delta":"+13.6"},{"date":"2020-11-16","black":"Fan Yin","blackElo":3290,"white":"Meng Tailing","whiteElo":3287,"result":"1-0","delta":"+9.9"},{"date":"2020-09-28","black":"Fan Yin","blackElo":3298,"white":"Li Weiqing","whiteElo":3384,"result":"0-1","delta":"-7.6"},{"date":"2020-09-21","black":"Fan Yin","blackElo":3290,"white":"Dang Yifei","whiteElo":3317,"result":"1-0","delta":"+10.8"},{"date":"2020-09-21","black":"Ke Jie","blackElo":3588,"white":"Fan Yin","whiteElo":3301,"result":"1-0","delta":"-3.2"},{"date":"2020-09-14","black":"Fan Tingyu","blackElo":3446,"white":"Fan Yin","whiteElo":3275,"result":"0-1","delta":"+14.6"},{"date":"2020-09-01","black":"Chen Xian","blackElo":3290,"white":"Fan Yin","whiteElo":3285,"result":"1-0","delta":"-9.9"},{"date":"2020-08-31","black":"Fan Yin","blackElo":3279,"white":"Chen Zhengxun","whiteElo":3129,"result":"1-0","delta":"+5.9"},{"date":"2020-08-30","black":"Zhang Qiang","blackElo":3101,"white":"Fan Yin","whiteElo":3274,"result":"0-1","delta":"+5.4"},{"date":"2020-08-29","black":"Gu Lingyi","blackElo":3131,"white":"Fan Yin","whiteElo":3288,"result":"1-0","delta":"-14.2"},{"date":"2020-08-27","black":"Fan Yin","blackElo":3295,"white":"Jiang Weijie","whiteElo":3424,"result":"0-1","delta":"-6.4"},{"date":"2020-08-26","black":"Fan Yin","blackElo":3288,"white":"Li Zhe","whiteElo":3177,"result":"1-0","delta":"+6.9"},{"date":"2020-08-25","black":"Hu Yaoyu","blackElo":3240,"white":"Fan Yin","whiteElo":3279,"result":"0-1","delta":"+8.9"},{"date":"2020-08-24","black":"Fan Yin","blackElo":3292,"white":"Liao Xingwen","whiteElo":3175,"result":"0-1","delta":"-13.3"},{"date":"2020-05-28","black":"Gu Zihao","blackElo":3493,"white":"Fan Yin","whiteElo":3297,"result":"1-0","delta":"-4.9"},{"date":"2020-04-13","black":"Fan Yin","blackElo":3303,"white":"Fan Yunruo","whiteElo":3437,"result":"0-1","delta":"-6.3"},{"date":"2020-03-18","black":"Fan Yin","blackElo":3314,"white":"Tan Xiao","whiteElo":3295,"result":"0-1","delta":"-10.6"},{"date":"2020-03-15","black":"Li Chengsen","blackElo":3195,"white":"Fan Yin","whiteElo":3307,"result":"0-1","delta":"+6.9"},{"date":"2020-03-11","black":"Fan Yin","blackElo":3313,"white":"Gu Zihao","whiteElo":3469,"result":"0-1","delta":"-5.8"},{"date":"2020-03-10","black":"Fan Yin","blackElo":3322,"white":"Dang Yifei","whiteElo":3356,"result":"0-1","delta":"-9.0"},{"date":"2020-03-06","black":"Fan Yin","blackElo":3315,"white":"Han Yizhou","whiteElo":3206,"result":"1-0","delta":"+7.0"},{"date":"2020-03-05","black":"Wu Guangya","blackElo":3269,"white":"Fan Yin","whiteElo":3327,"result":"1-0","delta":"-11.6"},{"date":"2020-03-01","black":"Huang Jingyuan","blackElo":3029,"white":"Fan Yin","whiteElo":3323,"result":"0-1","delta":"+3.1"},{"date":"2020-01-04","black":"Fan Yin","blackElo":3302,"white":"Jiang Weijie","whiteElo":3455,"result":"1-0","delta":"+14.2"},{"date":"2020-01-04","black":"Wang Haoyang","blackElo":3223,"white":"Fan Yin","whiteElo":3316,"result":"0-1","delta":"+7.4"},{"date":"2019-12-15","black":"Zhou Ruiyang","blackElo":3356,"white":"Fan Yin","whiteElo":3290,"result":"0-1","delta":"+11.9"},{"date":"2019-12-12","black":"Fan Yin","blackElo":3294,"white":"Mi Yuting","whiteElo":3541,"result":"0-1","delta":"-3.9"},{"date":"2019-12-11","black":"Huang Yunsong","blackElo":3332,"white":"Fan Yin","whiteElo":3283,"result":"0-1","delta":"+11.4"},{"date":"2019-12-09","black":"Chen Xian","blackElo":3273,"white":"Fan Yin","whiteElo":3293,"result":"1-0","delta":"-10.6"},{"date":"2019-11-15","black":"Fan Tingyu","blackElo":3412,"white":"Fan Yin","whiteElo":3300,"result":"1-0","delta":"-6.9"},{"date":"2019-11-06","black":"Lee Donghoon","blackElo":3364,"white":"Fan Yin","whiteElo":3308,"result":"1-0","delta":"-8.4"},{"date":"2019-11-04","black":"Fan Yin","blackElo":3314,"white":"Ding Hao","whiteElo":3456,"result":"0-1","delta":"-6.1"},{"date":"2019-10-10","black":"Yang Dingxin","blackElo":3496,"white":"Fan Yin","whiteElo":3320,"result":"1-0","delta":"-5.3"},{"date":"2019-08-26","black":"Kang Dongyun","blackElo":3288,"white":"Fan Yin","whiteElo":3310,"result":"0-1","delta":"+9.4"},{"date":"2019-08-24","black":"Fan Yin","blackElo":3301,"white":"Wu Guangya","whiteElo":3268,"result":"1-0","delta":"+9.0"},{"date":"2019-08-12","black":"Fan Yin","blackElo":3313,"white":"Wang Zejin","whiteElo":3249,"result":"0-1","delta":"-11.8"},{"date":"2019-08-10","black":"Yi Lingtao","blackElo":3323,"white":"Fan Yin","whiteElo":3303,"result":"0-1","delta":"+10.6"},{"date":"2019-07-29","black":"Fan Yin","blackElo":3318,"white":"Wang Xinghao","whiteElo":3100,"result":"0-1","delta":"-15.6"},{"date":"2019-07-22","black":"Fan Yin","blackElo":3322,"white":"Park Junghwan","whiteElo":3559,"result":"0-1","delta":"-4.1"},{"date":"2019-07-20","black":"Xu Jiayang","blackElo":3429,"white":"Fan Yin","whiteElo":3309,"result":"0-1","delta":"+13.3"},{"date":"2019-06-10","black":"Fan Yin","blackElo":3302,"white":"Huang Xin","whiteElo":3186,"result":"1-0","delta":"+6.8"},{"date":"2019-06-03","black":"Fan Yin","blackElo":3295,"white":"Shen Peiran","whiteElo":3178,"result":"1-0","delta":"+6.7"},{"date":"2019-06-01","black":"Tong Mengcheng","blackElo":3366,"white":"Fan Yin","whiteElo":3283,"result":"0-1","delta":"+12.3"},{"date":"2019-05-23","black":"Park Sangjin","blackElo":3125,"white":"Fan Yin","whiteElo":3277,"result":"0-1","delta":"+5.9"},{"date":"2019-05-11","black":"Fan Yin","blackElo":3271,"white":"Li Xiangyu","whiteElo":3116,"result":"1-0","delta":"+5.8"},{"date":"2019-05-09","black":"Fan Yin","blackElo":3276,"white":"Lian Xiao","whiteElo":3477,"result":"0-1","delta":"-4.8"},{"date":"2019-05-06","black":"Xie Ke","blackElo":3377,"white":"Fan Yin","whiteElo":3263,"result":"0-1","delta":"+13.2"},{"date":"2019-04-29","black":"Fan Yin","blackElo":3259,"white":"Chen Yusen","whiteElo":3041,"result":"1-0","delta":"+4.4"},{"date":"2019-04-22","black":"Fan Yin","blackElo":3263,"white":"Ke Jie","whiteElo":3504,"result":"0-1","delta":"-4.0"},{"date":"2019-04-17","black":"Han Yizhou","blackElo":3274,"white":"Fan Yin","whiteElo":3273,"result":"1-0","delta":"-10.0"},{"date":"2019-04-15","black":"Fan Yin","blackElo":3288,"white":"Wang Shiyi","whiteElo":3060,"result":"0-1","delta":"-15.8"},{"date":"2019-03-28","black":"Fan Yin","blackElo":3301,"white":"Sun Tengyu","whiteElo":3221,"result":"0-1","delta":"-12.2"},{"date":"2019-03-04","black":"Fan Yin","blackElo":3295,"white":"Hu Yuhan","whiteElo":3146,"result":"1-0","delta":"+6.0"},{"date":"2019-01-04","black":"Xie Erhao","blackElo":3462,"white":"Fan Yin","whiteElo":3280,"result":"0-1","delta":"+14.8"},{"date":"2018-12-27","black":"Gu Li","blackElo":3220,"white":"Fan Yin","whiteElo":3292,"result":"1-0","delta":"-12.0"},{"date":"2018-12-14","black":"Gu Li","blackElo":3205,"white":"Fan Yin","whiteElo":3305,"result":"1-0","delta":"-12.8"},{"date":"2018-12-12","black":"Kim Myounghoon","blackElo":3307,"white":"Fan Yin","whiteElo":3294,"result":"0-1","delta":"+10.4"},{"date":"2018-11-16","black":"Fan Yin","blackElo":3282,"white":"Tang Weixing","whiteElo":3355,"result":"1-0","delta":"+12.1"},{"date":"2018-11-09","black":"Wu Guangya","blackElo":3181,"white":"Fan Yin","whiteElo":3295,"result":"1-0","delta":"-13.2"},{"date":"2018-10-29","black":"Fan Yin","blackElo":3282,"white":"Jiang Weijie","whiteElo":3417,"result":"1-0","delta":"+13.7"},{"date":"2018-10-27","black":"Zhang Li","blackElo":3138,"white":"Fan Yin","whiteElo":3275,"result":"0-1","delta":"+6.2"},{"date":"2018-10-13","black":"Jiang Weijie","blackElo":3396,"white":"Fan Yin","whiteElo":3282,"result":"1-0","delta":"-6.8"},{"date":"2018-10-08","black":"Fan Yin","blackElo":3291,"white":"Xie Ke","whiteElo":3350,"result":"0-1","delta":"-8.3"},{"date":"2018-09-28","black":"Fan Yin","blackElo":3300,"white":"Zhao Chenyu","whiteElo":3335,"result":"0-1","delta":"-9.0"},{"date":"2018-09-12","black":"Jiang Qirun","blackElo":3051,"white":"Fan Yin","whiteElo":3296,"result":"0-1","delta":"+3.9"},{"date":"2018-09-10","black":"Fan Yin","blackElo":3304,"white":"Xu Jiayang","whiteElo":3373,"result":"0-1","delta":"-8.0"},{"date":"2018-08-13","black":"Tuo Jiaxi","blackElo":3386,"white":"Fan Yin","whiteElo":3312,"result":"1-0","delta":"-7.9"},{"date":"2018-08-06","black":"Fan Yin","blackElo":3321,"white":"Xie Erhao","whiteElo":3340,"result":"0-1","delta":"-9.4"},{"date":"2018-07-28","black":"Lee Sedol","blackElo":3370,"white":"Fan Yin","whiteElo":3321,"result":"0-1","delta":"+11.4"},{"date":"2018-07-28","black":"Fan Yin","blackElo":3333,"white":"Wang Yuanjun","whiteElo":3265,"result":"0-1","delta":"-11.9"},{"date":"2018-07-16","black":"Liu Xi (2)","blackElo":3162,"white":"Fan Yin","whiteElo":3316,"result":"0-1","delta":"+5.8"},{"date":"2018-06-29","black":"Fan Yin","blackElo":3321,"white":"Meng Tailing","whiteElo":3282,"result":"0-1","delta":"-11.1"},{"date":"2018-06-29","black":"Wang Chen","blackElo":3132,"white":"Fan Yin","whiteElo":3310,"result":"0-1","delta":"+5.3"},{"date":"2018-06-28","black":"Fan Yin","blackElo":3310,"white":"Chen Yunong","whiteElo":2977,"result":"1-0","delta":"+2.6"},{"date":"2018-06-28","black":"Yi Lingtao","blackElo":3266,"white":"Fan Yin","whiteElo":3313,"result":"0-1","delta":"+8.7"},{"date":"2018-06-02","black":"Fan Yin","blackElo":3323,"white":"Yi Lingtao","whiteElo":3221,"result":"0-1","delta":"-12.9"},{"date":"2018-05-28","black":"Fan Yin","blackElo":3330,"white":"Shin Jinseo","whiteElo":3460,"result":"0-1","delta":"-6.4"},{"date":"2018-05-21","black":"Huang Xin","blackElo":3090,"white":"Fan Yin","whiteElo":3346,"result":"1-0","delta":"-16.3"},{"date":"2018-05-16","black":"Fan Yin","blackElo":3363,"white":"Yan Zaiming","whiteElo":3051,"result":"0-1","delta":"-17.1"},{"date":"2018-05-14","black":"Tao Xinran","blackElo":3305,"white":"Fan Yin","whiteElo":3354,"result":"0-1","delta":"+8.6"},{"date":"2018-05-11","black":"Fan Yin","blackElo":3366,"white":"Peng Liyao","whiteElo":3294,"result":"0-1","delta":"-12.1"},{"date":"2018-05-09","black":"Xie Ke","blackElo":3363,"white":"Fan Yin","whiteElo":3356,"result":"0-1","delta":"+10.2"},{"date":"2018-04-25","black":"Fan Yin","blackElo":3367,"white":"Tong Mengcheng","whiteElo":3335,"result":"0-1","delta":"-10.9"},{"date":"2018-04-23","black":"Tuo Jiaxi","blackElo":3401,"white":"Fan Yin","whiteElo":3376,"result":"1-0","delta":"-9.3"},{"date":"2018-04-21","black":"Fan Yin","blackElo":3364,"white":"Ke Jie","whiteElo":3462,"result":"1-0","delta":"+12.8"},{"date":"2018-04-19","black":"Fan Yin","blackElo":3353,"white":"Tang Weixing","whiteElo":3378,"result":"1-0","delta":"+10.7"},{"date":"2018-04-09","black":"Fan Yin","blackElo":3353,"white":"Tang Weixing","whiteElo":3379,"result":"0-1","delta":"-9.2"},{"date":"2018-04-09","black":"Zhao Chenyu","blackElo":3323,"white":"Fan Yin","whiteElo":3344,"result":"0-1","delta":"+9.4"},{"date":"2018-04-07","black":"Fan Yin","blackElo":3350,"white":"Jeong Seojun","whiteElo":3023,"result":"1-0","delta":"+2.6"},{"date":"2018-04-02","black":"Fan Yin","blackElo":3343,"white":"Lee Changho","whiteElo":3240,"result":"1-0","delta":"+7.1"},{"date":"2018-03-30","black":"Zhang Tao","blackElo":3316,"white":"Fan Yin","whiteElo":3334,"result":"0-1","delta":"+9.5"},{"date":"2018-03-28","black":"Fan Yin","blackElo":3344,"white":"Byun Sangil","whiteElo":3325,"result":"0-1","delta":"-10.6"},{"date":"2018-01-25","black":"Fan Yin","blackElo":3354,"white":"Zhou Ruiyang","whiteElo":3360,"result":"0-1","delta":"-9.8"},{"date":"2018-01-23","black":"Fan Yin","blackElo":3351,"white":"Yan Zaiming","whiteElo":3009,"result":"1-0","delta":"+2.4"},{"date":"2018-01-15","black":"Fan Yin","blackElo":3360,"white":"Tuo Jiaxi","whiteElo":3404,"result":"0-1","delta":"-8.8"},{"date":"2018-01-10","black":"Fan Yin","blackElo":3352,"white":"Li Xuanhao","whiteElo":3305,"result":"1-0","delta":"+8.7"},{"date":"2018-01-08","black":"Meng Tailing","blackElo":3268,"white":"Fan Yin","whiteElo":3344,"result":"0-1","delta":"+7.9"},{"date":"2017-12-28","black":"Fan Yin","blackElo":3334,"white":"Zhang Tao","whiteElo":3313,"result":"1-0","delta":"+9.4"},{"date":"2017-12-27","black":"Fan Yin","blackElo":3326,"white":"Gu Lingyi","whiteElo":3253,"result":"1-0","delta":"+7.9"},{"date":"2017-12-26","black":"Fan Yin","blackElo":3313,"white":"Gu Zihao","whiteElo":3428,"result":"1-0","delta":"+13.2"},{"date":"2017-12-02","black":"Fan Tingyu","blackElo":3341,"white":"Fan Yin","whiteElo":3323,"result":"1-0","delta":"-9.5"},{"date":"2017-11-30","black":"Fan Yin","blackElo":3337,"white":"Li Weiqing","whiteElo":3161,"result":"0-1","delta":"-14.7"},{"date":"2017-11-22","black":"Fan Yin","blackElo":3328,"white":"Peng Liyao","whiteElo":3291,"result":"1-0","delta":"+8.9"},{"date":"2017-11-10","black":"Tuo Jiaxi","blackElo":3394,"white":"Fan Yin","whiteElo":3316,"result":"0-1","delta":"+12.2"},{"date":"2017-10-30","black":"Fan Yin","blackElo":3305,"white":"Ding Hao","whiteElo":3355,"result":"1-0","delta":"+11.4"},{"date":"2017-10-28","black":"Fan Yin","blackElo":3298,"white":"Wang Haoyang","whiteElo":3180,"result":"1-0","delta":"+6.7"},{"date":"2017-10-20","black":"Li Xuanhao","blackElo":3315,"white":"Fan Yin","whiteElo":3287,"result":"0-1","delta":"+10.8"},{"date":"2017-10-14","black":"Fan Yin","blackElo":3296,"white":"Lee Donghoon","whiteElo":3341,"result":"0-1","delta":"-8.7"},{"date":"2017-10-11","black":"Fan Yin","blackElo":3283,"white":"Tang Weixing","whiteElo":3389,"result":"1-0","delta":"+13.0"},{"date":"2017-10-10","black":"Zhou Hexi","blackElo":3270,"white":"Fan Yin","whiteElo":3273,"result":"0-1","delta":"+9.9"},{"date":"2017-10-08","black":"Fan Yin","blackElo":3280,"white":"Lian Xiao","whiteElo":3380,"result":"0-1","delta":"-7.2"},{"date":"2017-09-29","black":"Fan Yin","blackElo":3291,"white":"Dang Yifei","whiteElo":3251,"result":"0-1","delta":"-11.1"},{"date":"2017-09-26","black":"Fan Yin","blackElo":3306,"white":"Tu Xiaoyu","whiteElo":3122,"result":"0-1","delta":"-14.9"},{"date":"2017-09-22","black":"Liao Yuanhe","blackElo":3242,"white":"Fan Yin","whiteElo":3288,"result":"0-1","delta":"+8.7"},{"date":"2017-09-22","black":"Fan Yin","blackElo":3297,"white":"Xie Ke","whiteElo":3277,"result":"1-0","delta":"+9.4"},{"date":"2017-09-19","black":"Fan Yin","blackElo":3282,"white":"Hu Yuhan","whiteElo":3121,"result":"1-0","delta":"+5.7"},{"date":"2017-09-13","black":"Yang Kaiwen","blackElo":3197,"white":"Fan Yin","whiteElo":3295,"result":"1-0","delta":"-12.8"},{"date":"2017-09-02","black":"Chen Zhengxun","blackElo":3104,"white":"Fan Yin","whiteElo":3290,"result":"0-1","delta":"+5.1"},{"date":"2017-08-31","black":"Zhao Chenyu","blackElo":3239,"white":"Fan Yin","whiteElo":3281,"result":"0-1","delta":"+8.8"},{"date":"2017-08-28","black":"Yi Lingtao","blackElo":3004,"white":"Fan Yin","whiteElo":3278,"result":"0-1","delta":"+3.4"},{"date":"2017-08-22","black":"Fan Yin","blackElo":3263,"white":"Liu Xi (2)","whiteElo":3171,"result":"1-0","delta":"+14.8"},{"date":"2017-08-14","black":"Niu Yutian","blackElo":3226,"white":"Fan Yin","whiteElo":3225,"result":"1-0","delta":"-19.9"},{"date":"2017-08-14","black":"Fan Yin","blackElo":3205,"white":"Tan Xiao","whiteElo":3402,"result":"1-0","delta":"+30.3"},{"date":"2017-08-14","black":"Tang Weixing","blackElo":3384,"white":"Fan Yin","whiteElo":3235,"result":"0-1","delta":"+28.1"},{"date":"2017-08-11","black":"Fan Yin","blackElo":3202,"white":"Chen Zijian","whiteElo":3246,"result":"1-0","delta":"+22.5"},{"date":"2017-08-09","black":"Li Zhe","blackElo":3240,"white":"Fan Yin","whiteElo":3221,"result":"1-0","delta":"-18.9"},{"date":"2017-08-03","black":"Peng Liyao","blackElo":3319,"white":"Fan Yin","whiteElo":3236,"result":"1-0","delta":"-15.3"},{"date":"2017-07-19","black":"Fan Yin","blackElo":3250,"white":"Kim Jiseok","whiteElo":3359,"result":"0-1","delta":"-14.0"},{"date":"2017-07-17","black":"Fan Yin","blackElo":3231,"white":"Zhong Wenjing","whiteElo":3217,"result":"1-0","delta":"+19.2"},{"date":"2017-07-15","black":"Li Xiangyu","blackElo":3093,"white":"Fan Yin","whiteElo":3260,"result":"1-0","delta":"-28.9"},{"date":"2017-07-01","black":"Kim Jiseok","blackElo":3362,"white":"Fan Yin","whiteElo":3275,"result":"1-0","delta":"-15.1"},{"date":"2017-06-17","black":"Fan Yin","blackElo":3304,"white":"Cai Jing","whiteElo":3135,"result":"0-1","delta":"-29.1"},{"date":"2017-05-18","black":"Yang Dingxin","blackElo":3356,"white":"Fan Yin","whiteElo":3322,"result":"1-0","delta":"-18.1"},{"date":"2017-05-16","black":"Fan Yin","blackElo":3308,"white":"Wu Guangya","whiteElo":3202,"result":"1-0","delta":"+14.1"},{"date":"2017-05-14","black":"Gu Lingyi","blackElo":3263,"white":"Fan Yin","whiteElo":3332,"result":"1-0","delta":"-23.9"},{"date":"2017-05-05","black":"Fan Yin","blackElo":3318,"white":"Hu Yuefeng","whiteElo":3207,"result":"1-0","delta":"+13.8"},{"date":"2017-05-03","black":"Meng Tailing","blackElo":3278,"white":"Fan Yin","whiteElo":3342,"result":"1-0","delta":"-23.6"},{"date":"2017-04-27","black":"Fan Yin","blackElo":3364,"white":"Tong Mengcheng","whiteElo":3326,"result":"0-1","delta":"-22.2"},{"date":"2017-04-25","black":"Fan Yin","blackElo":3353,"white":"Zhang Li","whiteElo":3192,"result":"1-0","delta":"+11.4"},{"date":"2017-04-18","black":"Li Xuanhao","blackElo":3314,"white":"Fan Yin","whiteElo":3367,"result":"0-1","delta":"+16.9"},{"date":"2017-04-18","black":"Yang Kaiwen","blackElo":3159,"white":"Fan Yin","whiteElo":3384,"result":"1-0","delta":"-31.4"},{"date":"2017-03-04","black":"Park Geunho","blackElo":2976,"white":"Fan Yin","whiteElo":3363,"result":"0-1","delta":"+3.9"},{"date":"2017-03-01","black":"Liu Yuhang","blackElo":3020,"white":"Fan Yin","whiteElo":3358,"result":"0-1","delta":"+5.0"},{"date":"2017-02-22","black":"Fan Yin","blackElo":3344,"white":"Sun Tengyu","whiteElo":3242,"result":"1-0","delta":"+14.3"},{"date":"2017-02-20","black":"Fan Yin","blackElo":3331,"white":"Zhang Li","whiteElo":3199,"result":"1-0","delta":"+12.7"},{"date":"2017-02-17","black":"Fan Yin","blackElo":3325,"white":"Shu Yixiao","whiteElo":3048,"result":"1-0","delta":"+6.8"},{"date":"2017-01-16","black":"Lian Xiao","blackElo":3398,"white":"Fan Yin","whiteElo":3341,"result":"1-0","delta":"-16.7"},{"date":"2017-01-14","black":"Fan Yin","blackElo":3321,"white":"Yu Zhiying","whiteElo":3326,"result":"1-0","delta":"+20.3"},{"date":"2016-12-24","black":"Zhou Ruiyang","blackElo":3420,"white":"Fan Yin","whiteElo":3336,"result":"1-0","delta":"-15.3"},{"date":"2016-12-03","black":"Li Xuanhao","blackElo":3331,"white":"Fan Yin","whiteElo":3315,"result":"0-1","delta":"+20.9"},{"date":"2016-12-01","black":"Fan Yin","blackElo":3340,"white":"Zhou Hexi","whiteElo":3265,"result":"0-1","delta":"-24.2"},{"date":"2016-11-21","black":"Xu Jiayang","blackElo":3298,"white":"Fan Yin","whiteElo":3363,"result":"1-0","delta":"-23.7"},{"date":"2016-11-18","black":"Ding Shixiong","blackElo":3066,"white":"Fan Yin","whiteElo":3357,"result":"0-1","delta":"+6.3"},{"date":"2016-11-14","black":"Fan Yin","blackElo":3336,"white":"Gu Zihao","whiteElo":3352,"result":"1-0","delta":"+20.9"},{"date":"2016-11-06","black":"Fan Yin","blackElo":3355,"white":"Fan Yunruo","whiteElo":3381,"result":"0-1","delta":"-18.5"},{"date":"2016-11-04","black":"Han Yizhou","blackElo":3101,"white":"Fan Yin","whiteElo":3347,"result":"0-1","delta":"+7.8"},{"date":"2016-10-28","black":"Fan Yin","blackElo":3335,"white":"Wu Guangya","whiteElo":3180,"result":"1-0","delta":"+11.6"},{"date":"2016-10-25","black":"Fan Yin","blackElo":3366,"white":"Xie Ke","whiteElo":3151,"result":"0-1","delta":"-31.0"},{"date":"2016-10-10","black":"Fan Yin","blackElo":3349,"white":"Liao Yuanhe","whiteElo":3300,"result":"1-0","delta":"+17.2"},{"date":"2016-10-08","black":"Fan Yin","blackElo":3339,"white":"Li Ming","whiteElo":3146,"result":"1-0","delta":"+9.9"},{"date":"2016-09-26","black":"Zhong Wenjing","blackElo":3213,"white":"Fan Yin","whiteElo":3325,"result":"0-1","delta":"+13.7"},{"date":"2016-09-25","black":"Ding Hao","blackElo":3213,"white":"Fan Yin","whiteElo":3311,"result":"0-1","delta":"+14.5"},{"date":"2016-09-23","black":"Fan Yin","blackElo":3297,"white":"Guo Yuzheng","whiteElo":3189,"result":"1-0","delta":"+14.0"},{"date":"2016-09-22","black":"Xie Erhao","blackElo":3330,"white":"Fan Yin","whiteElo":3274,"result":"0-1","delta":"+23.2"},{"date":"2016-09-20","black":"Fan Yin","blackElo":3260,"white":"Zhang Tao","whiteElo":3147,"result":"1-0","delta":"+13.7"},{"date":"2016-09-19","black":"Xu Jiayang","blackElo":3301,"white":"Fan Yin","whiteElo":3236,"result":"0-1","delta":"+23.7"},{"date":"2016-09-17","black":"Fu Chong","blackElo":3148,"white":"Fan Yin","whiteElo":3221,"result":"0-1","delta":"+15.9"},{"date":"2016-09-16","black":"Fan Yin","blackElo":3200,"white":"Rong Yi","whiteElo":3212,"result":"1-0","delta":"+20.7"},{"date":"2016-09-12","black":"Fan Yin","blackElo":3216,"white":"Meng Tailing","whiteElo":3279,"result":"0-1","delta":"-16.4"},{"date":"2016-09-10","black":"Fan Yin","blackElo":3187,"white":"Tong Mengcheng","whiteElo":3371,"result":"1-0","delta":"+29.7"},{"date":"2016-08-25","black":"Weon Seongjin","blackElo":3333,"white":"Fan Yin","whiteElo":3199,"result":"1-0","delta":"-12.7"},{"date":"2016-08-09","black":"Fan Yin","blackElo":3229,"white":"Qiao Zhijian","whiteElo":3050,"result":"0-1","delta":"-29.5"},{"date":"2016-08-07","black":"Park Hamin","blackElo":3079,"white":"Fan Yin","whiteElo":3216,"result":"0-1","delta":"+12.5"},{"date":"2016-07-04","black":"Fan Yin","blackElo":3190,"white":"Yang Dingxin","whiteElo":3295,"result":"1-0","delta":"+25.8"},{"date":"2016-07-02","black":"Fan Yin","blackElo":3158,"white":"Shi Yue","whiteElo":3398,"result":"1-0","delta":"+31.9"},{"date":"2016-06-30","black":"Fan Yin","blackElo":3133,"white":"Mao Ruilong","whiteElo":3225,"result":"1-0","delta":"+25.2"},{"date":"2016-06-28","black":"Terayama Rei","blackElo":3179,"white":"Fan Yin","whiteElo":3109,"result":"0-1","delta":"+24.0"},{"date":"2016-06-06","black":"Gu Zihao","blackElo":3422,"white":"Fan Yin","whiteElo":3115,"result":"1-0","delta":"-5.8"},{"date":"2016-05-22","black":"Fan Yin","blackElo":3122,"white":"Tuo Jiaxi","whiteElo":3410,"result":"0-1","delta":"-6.4"},{"date":"2016-05-18","black":"Mi Yuting","blackElo":3418,"white":"Fan Yin","whiteElo":3128,"result":"1-0","delta":"-6.3"},{"date":"2016-05-03","black":"Huang Xin","blackElo":3096,"white":"Fan Yin","whiteElo":3109,"result":"0-1","delta":"+19.3"},{"date":"2016-05-02","black":"Fan Yin","blackElo":3095,"white":"Zhou Yuanjun","whiteElo":2983,"result":"1-0","delta":"+13.8"},{"date":"2016-05-01","black":"Fan Yin","blackElo":3081,"white":"Cheng Guan","whiteElo":2979,"result":"1-0","delta":"+14.3"},{"date":"2016-04-28","black":"Park Hamin","blackElo":3049,"white":"Fan Yin","whiteElo":3104,"result":"1-0","delta":"-23.1"},{"date":"2016-04-26","black":"Liu Qifeng","blackElo":2991,"white":"Fan Yin","whiteElo":3101,"result":"0-1","delta":"+13.9"},{"date":"2016-04-26","black":"Fan Yin","blackElo":3115,"white":"Shin Minjun","whiteElo":3281,"result":"0-1","delta":"-11.1"},{"date":"2016-04-13","black":"Fan Yin","blackElo":3114,"white":"Xie Erhao","whiteElo":3242,"result":"0-1","delta":"-13.0"},{"date":"2016-04-11","black":"Huang Yunsong","blackElo":3359,"white":"Fan Yin","whiteElo":3122,"result":"1-0","delta":"-8.1"},{"date":"2015-09-18","black":"Fan Yin","blackElo":3134,"white":"Yang Dingxin","whiteElo":3290,"result":"0-1","delta":"-11.6"},{"date":"2015-08-23","black":"Fan Yunruo","blackElo":3262,"white":"Fan Yin","whiteElo":3147,"result":"1-0","delta":"-13.6"},{"date":"2015-07-27","black":"Fan Yin","blackElo":3129,"white":"Qiao Zhijian","whiteElo":3097,"result":"1-0","delta":"+18.2"},{"date":"2015-07-26","black":"Song Ronghui","blackElo":3080,"white":"Fan Yin","whiteElo":3111,"result":"0-1","delta":"+18.2"},{"date":"2015-07-25","black":"Chen Xiaonan","blackElo":3163,"white":"Fan Yin","whiteElo":3129,"result":"1-0","delta":"-18.0"},{"date":"2015-07-24","black":"Chen Xian","blackElo":3166,"white":"Fan Yin","whiteElo":3148,"result":"1-0","delta":"-19.0"},{"date":"2015-07-22","black":"Zhang Qiang","blackElo":3185,"white":"Fan Yin","whiteElo":3124,"result":"0-1","delta":"+23.4"},{"date":"2015-07-21","black":"Fan Yin","blackElo":3094,"white":"Yang Kaiwen","whiteElo":3287,"result":"1-0","delta":"+30.1"},{"date":"2015-07-20","black":"Fan Yin","blackElo":3084,"white":"Li Huasong","whiteElo":2900,"result":"1-0","delta":"+10.3"},{"date":"2015-07-19","black":"Fan Yin","blackElo":3061,"white":"Gan Siyang","whiteElo":3106,"result":"1-0","delta":"+22.6"},{"date":"2015-07-14","black":"Fan Yin","blackElo":3078,"white":"Qin Yuexin","whiteElo":3140,"result":"0-1","delta":"-16.5"},{"date":"2015-07-09","black":"Li Qincheng","blackElo":3403,"white":"Fan Yin","whiteElo":3083,"result":"1-0","delta":"-5.5"},{"date":"2015-07-07","black":"Liu Xi (2)","blackElo":3184,"white":"Fan Yin","whiteElo":3056,"result":"0-1","delta":"+27.1"},{"date":"2015-06-27","black":"Fan Yin","blackElo":3075,"white":"Liao Yuanhe","whiteElo":3096,"result":"0-1","delta":"-18.8"},{"date":"2015-05-19","black":"Gan Siyang","blackElo":3177,"white":"Fan Yin","whiteElo":3048,"result":"0-1","delta":"+27.1"},{"date":"2014-06-25","black":"Li Qincheng","blackElo":3345,"white":"Fan Yin","whiteElo":3054,"result":"1-0","delta":"-6.3"},{"date":"2014-03-23","black":"Fan Yin","blackElo":3072,"white":"Zhao Chenyu","whiteElo":3119,"result":"0-1","delta":"-17.3"},{"date":"2014-03-20","black":"Xie Ke","blackElo":3049,"white":"Fan Yin","whiteElo":3052,"result":"0-1","delta":"+19.9"},{"date":"2013-12-30","black":"Fan Yin","blackElo":3058,"white":"Lian Xiao","whiteElo":3342,"result":"0-1","delta":"-6.5"},{"date":"2013-12-29","black":"Tang Yi","blackElo":3070,"white":"Fan Yin","whiteElo":3036,"result":"0-1","delta":"+22.0"},{"date":"2013-12-28","black":"Fan Yin","blackElo":3044,"white":"Huang Yunsong","whiteElo":3293,"result":"0-1","delta":"-7.7"},{"date":"2013-12-27","black":"Chen Yunong","blackElo":3021,"white":"Fan Yin","whiteElo":3024,"result":"0-1","delta":"+19.8"},{"date":"2013-12-10","black":"Fan Yin","blackElo":3005,"white":"Wu Zhenyu (s)","whiteElo":3000,"result":"1-0","delta":"+19.7"},{"date":"2013-09-24","black":"Zhou Yuanjun","blackElo":2991,"white":"Fan Yin","whiteElo":2984,"result":"0-1","delta":"+20.4"},{"date":"2013-09-18","black":"Gu Lingyi","blackElo":3309,"white":"Fan Yin","whiteElo":2990,"result":"1-0","delta":"-5.5"},{"date":"2012-12-28","black":"Fan Yin","blackElo":2996,"white":"Hu Yaoyu","whiteElo":3278,"result":"0-1","delta":"-6.6"},{"date":"2012-12-26","black":"Fan Yin","blackElo":3014,"white":"Huang Yunsong","whiteElo":3046,"result":"0-1","delta":"-18.2"},{"date":"2012-08-10","black":"Zhang Li","blackElo":3199,"white":"Fan Yin","whiteElo":3025,"result":"1-0","delta":"-10.7"},{"date":"2012-08-09","black":"Gao Yu","blackElo":2978,"white":"Fan Yin","whiteElo":3007,"result":"0-1","delta":"+18.3"},{"date":"2011-12-30","black":"Meng Tailing","blackElo":3329,"white":"Fan Yin","whiteElo":3012,"result":"1-0","delta":"-5.6"},{"date":"2011-12-29","black":"Liu Xing","blackElo":3230,"white":"Fan Yin","whiteElo":2980,"result":"0-1","delta":"+32.3"},{"date":"2011-12-28","black":"Li Xiangyu","blackElo":3000,"white":"Fan Yin","whiteElo":3000,"result":"1-0","delta":"-20.0"}]
