[{"date":"2015-12-19","black":"Shi Yue","blackElo":3426,"white":"Guo Yiming","whiteElo":2927,"result":"1-0","delta":"-2.1"},{"date":"2015-12-17","black":"Guo Yiming","blackElo":2935,"white":"Chang Hao","whiteElo":3177,"result":"0-1","delta":"-8.0"},{"date":"2015-12-16","black":"Chen Zhixuan","blackElo":2973,"white":"Guo Yiming","whiteElo":2954,"result":"1-0","delta":"-18.9"},{"date":"2013-12-23","black":"Kobayashi Koichi","blackElo":3086,"white":"Guo Yiming","whiteElo":2967,"result":"1-0","delta":"-13.4"},{"date":"2013-12-21","black":"Chang Hao","blackElo":3163,"white":"Guo Yiming","whiteElo":2977,"result":"1-0","delta":"-10.2"},{"date":"2002-06-03","black":"Guo Yiming","blackElo":3000,"white":"Fu Li","whiteElo":2956,"result":"0-1","delta":"-22.5"}]
