[{"date":"2025-05-19","black":"Tsuruyama Atsushi","blackElo":3185,"white":"Hamakado Hibiki","whiteElo":2999,"result":"1-0","delta":"-10.2"},{"date":"2025-05-08","black":"Hamakado Hibiki","blackElo":3003,"white":"Fukuoka Kotaro","whiteElo":3359,"result":"0-1","delta":"-4.6"},{"date":"2025-04-21","black":"Hamakado Hibiki","blackElo":2996,"white":"Rin Kaiho","whiteElo":2742,"result":"1-0","delta":"+7.6"},{"date":"2025-04-14","black":"Aoki Shinichi","blackElo":2856,"white":"Hamakado Hibiki","whiteElo":2983,"result":"0-1","delta":"+13.0"},{"date":"2025-04-10","black":"Imabun Taro","blackElo":3100,"white":"Hamakado Hibiki","whiteElo":2955,"result":"0-1","delta":"+27.9"},{"date":"2025-01-09","black":"Uchida Shuhei","blackElo":3003,"white":"Hamakado Hibiki","whiteElo":2973,"result":"1-0","delta":"-18.3"},{"date":"2024-01-18","black":"Anzai Nobuaki","blackElo":3226,"white":"Hamakado Hibiki","whiteElo":2981,"result":"1-0","delta":"-7.8"},{"date":"2023-09-18","black":"Kuwabara Itsuki","blackElo":3013,"white":"Hamakado Hibiki","whiteElo":3000,"result":"1-0","delta":"-19.3"}]
