[{"date":"2007-07-24","black":"Xu Feiran","blackElo":2999,"white":"Hu Lei","whiteElo":2935,"result":"1-0","delta":"-16.4"},{"date":"2007-07-23","black":"Hu Lei","blackElo":2949,"white":"Tang Yi","whiteElo":3056,"result":"0-1","delta":"-14.1"},{"date":"2007-07-20","black":"Hu Lei","blackElo":2968,"white":"Pan Fei","whiteElo":2992,"result":"0-1","delta":"-18.6"},{"date":"2007-07-13","black":"Hu Lei","blackElo":2980,"white":"Zheng Yan","whiteElo":3119,"result":"0-1","delta":"-12.4"},{"date":"2007-07-12","black":"Qin Yuexin","blackElo":2973,"white":"Hu Lei","whiteElo":3002,"result":"1-0","delta":"-21.7"},{"date":"2007-07-11","black":"Hu Shuai","blackElo":3000,"white":"Hu Lei","whiteElo":2981,"result":"0-1","delta":"+21.1"},{"date":"2005-07-11","black":"Meng Zhaoyu","blackElo":3018,"white":"Hu Lei","whiteElo":3000,"result":"1-0","delta":"-19.0"}]
