[{"date":"2024-12-02","black":"Zhou Ziyi","blackElo":3105,"white":"Huang Qiuxuan","whiteElo":2941,"result":"1-0","delta":"-11.2"},{"date":"2024-12-01","black":"Wang Ruoyu","blackElo":3079,"white":"Huang Qiuxuan","whiteElo":2925,"result":"1-0","delta":"-11.7"},{"date":"2024-12-01","black":"Huang Qiuxuan","blackElo":2913,"white":"Yin Chengzhi","whiteElo":3058,"result":"1-0","delta":"+27.9"},{"date":"2024-11-30","black":"Huang Qiuxuan","blackElo":2949,"white":"Li Xinchen","whiteElo":3028,"result":"0-1","delta":"-15.5"},{"date":"2024-11-30","black":"Huang Qiuxuan","blackElo":2933,"white":"Ye Changxin","whiteElo":3166,"result":"0-1","delta":"-8.3"},{"date":"2024-11-29","black":"Huang Qiuxuan","blackElo":2971,"white":"Fu Jianheng","whiteElo":3147,"result":"0-1","delta":"-10.7"},{"date":"2024-11-29","black":"Xu Yidi","blackElo":3110,"white":"Huang Qiuxuan","whiteElo":2961,"result":"1-0","delta":"-11.9"},{"date":"2024-03-30","black":"Huang Qiuxuan","blackElo":2991,"white":"Tian Mumu","whiteElo":3003,"result":"0-1","delta":"-19.3"},{"date":"2023-09-24","black":"Hu Zihao","blackElo":3205,"white":"Huang Qiuxuan","whiteElo":3000,"result":"1-0","delta":"-9.4"}]
