[{"date":"2024-02-21","black":"Kageyama Toshiyuki","blackElo":2947,"white":"Fujita Reo","whiteElo":2944,"result":"0-1","delta":"-20.2"},{"date":"2017-05-31","black":"Ha Youngil","blackElo":3011,"white":"Kageyama Toshiyuki","whiteElo":2965,"result":"1-0","delta":"-17.4"},{"date":"2017-05-10","black":"Kageyama Toshiyuki","blackElo":2985,"white":"Hara Masakazu","whiteElo":2981,"result":"0-1","delta":"-20.2"},{"date":"2014-11-19","black":"Sonoda Yuichi","blackElo":3090,"white":"Kageyama Toshiyuki","whiteElo":3000,"result":"1-0","delta":"-14.9"}]
