[{"date":"2011-03-21","black":"Kang Dongyun","blackElo":3336,"white":"Yeom Jeonghun","whiteElo":2910,"result":"1-0","delta":"-3.2"},{"date":"2011-01-24","black":"Yeom Jeonghun","blackElo":2878,"white":"Ko Keuntae","whiteElo":3119,"result":"1-0","delta":"+32.0"},{"date":"2010-07-26","black":"Yeom Jeonghun","blackElo":2890,"white":"Hong Kipyo","whiteElo":3042,"result":"0-1","delta":"-11.8"},{"date":"2009-11-04","black":"Jin Donggyu","blackElo":3038,"white":"Yeom Jeonghun","whiteElo":2903,"result":"1-0","delta":"-12.6"},{"date":"2009-10-30","black":"Ko Keuntae","blackElo":3165,"white":"Yeom Jeonghun","whiteElo":2910,"result":"1-0","delta":"-7.5"},{"date":"2009-10-04","black":"Yeom Jeonghun","blackElo":2915,"white":"Lee Yeonggu","whiteElo":3258,"result":"0-1","delta":"-4.9"},{"date":"2009-09-25","black":"Yeom Jeonghun","blackElo":2879,"white":"Heo Yongho","whiteElo":3291,"result":"1-0","delta":"+36.6"},{"date":"2009-09-19","black":"Paek Hongseok","blackElo":3242,"white":"Yeom Jeonghun","whiteElo":2883,"result":"1-0","delta":"-4.5"},{"date":"2009-09-04","black":"Yeom Jeonghun","blackElo":2855,"white":"Kim Hyunsub","whiteElo":3000,"result":"1-0","delta":"+27.9"},{"date":"2009-08-28","black":"Jin Donggyu","blackElo":3055,"white":"Yeom Jeonghun","whiteElo":2865,"result":"1-0","delta":"-10.0"},{"date":"2009-08-12","black":"Yeom Jeonghun","blackElo":2877,"white":"Kwon Hyungjin","whiteElo":3024,"result":"0-1","delta":"-12.0"},{"date":"2009-07-24","black":"Lee Wondo","blackElo":3113,"white":"Yeom Jeonghun","whiteElo":2886,"result":"1-0","delta":"-8.5"},{"date":"2009-06-28","black":"Kim Seongjae","blackElo":3079,"white":"Yeom Jeonghun","whiteElo":2896,"result":"1-0","delta":"-10.3"},{"date":"2009-02-28","black":"Cho Hyeyeon","blackElo":3101,"white":"Yeom Jeonghun","whiteElo":2906,"result":"1-0","delta":"-9.8"},{"date":"2008-04-16","black":"Yeom Jeonghun","blackElo":2920,"white":"Park Jinyeol","whiteElo":3020,"result":"0-1","delta":"-14.4"},{"date":"2008-02-02","black":"Yun Hyuk","blackElo":2942,"white":"Yeom Jeonghun","whiteElo":2940,"result":"1-0","delta":"-19.9"},{"date":"2008-01-10","black":"Yeom Jeonghun","blackElo":2946,"white":"Hong Seongji","whiteElo":3269,"result":"0-1","delta":"-5.4"},{"date":"2007-09-06","black":"Yeom Jeonghun","blackElo":2964,"white":"Jen Youngkyu","whiteElo":2986,"result":"0-1","delta":"-18.7"},{"date":"2007-07-13","black":"Park Yeonghun","blackElo":3333,"white":"Yeom Jeonghun","whiteElo":2969,"result":"1-0","delta":"-4.4"},{"date":"2007-04-05","black":"Han Sanghoon","blackElo":3000,"white":"Yeom Jeonghun","whiteElo":2988,"result":"1-0","delta":"-19.3"},{"date":"2006-07-10","black":"Yeom Jeonghun","blackElo":3001,"white":"Jin Siyoung","whiteElo":3126,"result":"0-1","delta":"-13.1"},{"date":"2003-10-09","black":"Yeom Jeonghun","blackElo":3008,"white":"An Joyeong","whiteElo":3285,"result":"0-1","delta":"-6.7"},{"date":"2003-04-10","black":"Park Seunghyeon","blackElo":2976,"white":"Yeom Jeonghun","whiteElo":3031,"result":"1-0","delta":"-23.1"},{"date":"2002-12-02","black":"Paek Hongseok","blackElo":2991,"white":"Yeom Jeonghun","whiteElo":3055,"result":"1-0","delta":"-23.6"},{"date":"2002-11-22","black":"Song Taekon","blackElo":3215,"white":"Yeom Jeonghun","whiteElo":3025,"result":"0-1","delta":"+30.0"},{"date":"2002-09-02","black":"Heo Yongho","blackElo":3021,"white":"Yeom Jeonghun","whiteElo":3004,"result":"0-1","delta":"+21.0"},{"date":"2002-07-24","black":"Kim Seonryong","blackElo":3124,"white":"Yeom Jeonghun","whiteElo":3018,"result":"1-0","delta":"-14.1"},{"date":"2002-07-19","black":"Yeom Jeonghun","blackElo":3040,"white":"Park Byeongkyu","whiteElo":3005,"result":"0-1","delta":"-22.0"},{"date":"2002-07-09","black":"Kim Kangkeun","blackElo":2931,"white":"Yeom Jeonghun","whiteElo":3025,"result":"0-1","delta":"+14.7"},{"date":"2002-07-05","black":"Kim Yeonghwan","blackElo":3160,"white":"Yeom Jeonghun","whiteElo":2996,"result":"0-1","delta":"+28.8"},{"date":"2002-06-05","black":"An Younggil","blackElo":3106,"white":"Yeom Jeonghun","whiteElo":3011,"result":"1-0","delta":"-14.6"},{"date":"2002-04-17","black":"Paek Daehyun","blackElo":3006,"white":"Yeom Jeonghun","whiteElo":3032,"result":"1-0","delta":"-21.5"},{"date":"2002-03-21","black":"Yeom Jeonghun","blackElo":3044,"white":"Cho Hanseung","whiteElo":3200,"result":"0-1","delta":"-11.6"},{"date":"2002-03-06","black":"Yeom Jeonghun","blackElo":3010,"white":"Lee Sedol","whiteElo":3300,"result":"1-0","delta":"+33.6"},{"date":"2002-01-25","black":"Yeom Jeonghun","blackElo":2979,"white":"Choi Myeonghun","whiteElo":3211,"result":"1-0","delta":"+31.7"},{"date":"2001-10-30","black":"Yeom Jeonghun","blackElo":2995,"white":"Park Seungcheol","whiteElo":3051,"result":"0-1","delta":"-16.8"},{"date":"2001-09-14","black":"Yeom Jeonghun","blackElo":3000,"white":"Yoo Changhyuk","whiteElo":3352,"result":"0-1","delta":"-4.7"}]
