[{"date":"2025-07-26","black":"Han Jooyoung","blackElo":3007,"white":"Yun Chanhee","whiteElo":3171,"result":"1-0","delta":"-14.4"},{"date":"2025-07-20","black":"Park Jinsol","blackElo":3253,"white":"Yun Chanhee","whiteElo":3179,"result":"1-0","delta":"-7.9"},{"date":"2025-07-19","black":"Yun Chanhee","blackElo":3177,"white":"Kim Sangin","whiteElo":2796,"result":"1-0","delta":"+2.0"},{"date":"2025-04-30","black":"Moon Minjong","blackElo":3267,"white":"Yun Chanhee","whiteElo":3184,"result":"1-0","delta":"-7.7"},{"date":"2023-07-03","black":"Yun Chanhee","blackElo":3192,"white":"Sim Jaeik","whiteElo":3274,"result":"0-1","delta":"-7.7"},{"date":"2023-06-27","black":"Han Woojin","blackElo":3333,"white":"Yun Chanhee","whiteElo":3198,"result":"1-0","delta":"-6.3"},{"date":"2023-05-18","black":"Park Minkyu","blackElo":3284,"white":"Yun Chanhee","whiteElo":3206,"result":"1-0","delta":"-7.8"},{"date":"2023-04-28","black":"Yun Chanhee","blackElo":3214,"white":"Kang Seungmin","whiteElo":3297,"result":"0-1","delta":"-7.6"},{"date":"2023-04-23","black":"Kim Junghyun","blackElo":3215,"white":"Yun Chanhee","whiteElo":3203,"result":"0-1","delta":"+10.3"},{"date":"2023-04-17","black":"Song Sanghun","blackElo":3030,"white":"Yun Chanhee","whiteElo":3198,"result":"0-1","delta":"+5.5"},{"date":"2023-03-30","black":"Yun Chanhee","blackElo":3209,"white":"Baek Hyeonwoo","whiteElo":3151,"result":"0-1","delta":"-11.7"},{"date":"2023-03-26","black":"Yun Chanhee","blackElo":3214,"white":"Shin Minjun","whiteElo":3447,"result":"0-1","delta":"-4.1"},{"date":"2023-03-15","black":"Yun Chanhee","blackElo":3197,"white":"Xu Haohong","whiteElo":3492,"result":"1-0","delta":"+16.9"},{"date":"2023-02-23","black":"Park Minkyu","blackElo":3241,"white":"Yun Chanhee","whiteElo":3206,"result":"1-0","delta":"-9.0"},{"date":"2023-02-20","black":"Park Jaekeun","blackElo":3202,"white":"Yun Chanhee","whiteElo":3195,"result":"0-1","delta":"+10.2"},{"date":"2023-02-12","black":"Lee Jihyun (m)","blackElo":3361,"white":"Yun Chanhee","whiteElo":3181,"result":"0-1","delta":"+14.8"},{"date":"2023-02-07","black":"Yun Chanhee","blackElo":3172,"white":"Han Wonggyu","whiteElo":3112,"result":"1-0","delta":"+8.3"},{"date":"2023-02-06","black":"Kim Sehyun","blackElo":3027,"white":"Yun Chanhee","whiteElo":3166,"result":"0-1","delta":"+6.2"},{"date":"2023-01-23","black":"Jin Siyoung","blackElo":3157,"white":"Yun Chanhee","whiteElo":3156,"result":"0-1","delta":"+10.0"},{"date":"2023-01-15","black":"Yun Chanhee","blackElo":3144,"white":"Hirose Yuichi","whiteElo":3205,"result":"1-0","delta":"+11.7"},{"date":"2023-01-14","black":"Hong Mujin","blackElo":3262,"white":"Yun Chanhee","whiteElo":3151,"result":"1-0","delta":"-6.9"},{"date":"2023-01-09","black":"Yun Chanhee","blackElo":3159,"white":"Kang Yootaek","whiteElo":3249,"result":"0-1","delta":"-7.5"},{"date":"2022-12-28","black":"Xu Haohong","blackElo":3541,"white":"Yun Chanhee","whiteElo":3161,"result":"1-0","delta":"-2.0"},{"date":"2022-12-05","black":"Kim Chaeyoung","blackElo":3202,"white":"Yun Chanhee","whiteElo":3170,"result":"1-0","delta":"-9.1"},{"date":"2022-05-05","black":"Lee Changseok","blackElo":3329,"white":"Yun Chanhee","whiteElo":3176,"result":"1-0","delta":"-5.9"},{"date":"2022-04-26","black":"Seol Hyunjun","blackElo":3293,"white":"Yun Chanhee","whiteElo":3183,"result":"1-0","delta":"-6.9"},{"date":"2022-04-19","black":"Heo Youngrak","blackElo":3159,"white":"Yun Chanhee","whiteElo":3173,"result":"0-1","delta":"+9.6"},{"date":"2022-04-11","black":"Byun Sangil","blackElo":3494,"white":"Yun Chanhee","whiteElo":3176,"result":"1-0","delta":"-2.8"},{"date":"2022-04-07","black":"Yun Chanhee","blackElo":3178,"white":"Park Junghwan","whiteElo":3549,"result":"0-1","delta":"-2.1"},{"date":"2022-04-03","black":"Han Sanghoon","blackElo":3204,"white":"Yun Chanhee","whiteElo":3197,"result":"1-0","delta":"-9.8"},{"date":"2022-04-03","black":"Yun Chanhee","blackElo":3188,"white":"Song Gyusang","whiteElo":3199,"result":"0-1","delta":"-9.7"},{"date":"2022-04-02","black":"Lee Wonyoung","blackElo":3237,"white":"Yun Chanhee","whiteElo":3207,"result":"1-0","delta":"-9.1"},{"date":"2022-04-01","black":"Yun Chanhee","blackElo":3194,"white":"Park Jinsol","whiteElo":3288,"result":"1-0","delta":"+12.7"},{"date":"2022-03-31","black":"Park Sangjin","blackElo":3220,"white":"Yun Chanhee","whiteElo":3194,"result":"0-1","delta":"+10.7"},{"date":"2022-03-31","black":"Song Gyusang","blackElo":3193,"white":"Yun Chanhee","whiteElo":3204,"result":"1-0","delta":"-10.3"},{"date":"2022-03-17","black":"Yun Chanhee","blackElo":3205,"white":"Kim Jinhwi","whiteElo":3167,"result":"0-1","delta":"-11.1"},{"date":"2022-03-15","black":"Hong Mujin","blackElo":3250,"white":"Yun Chanhee","whiteElo":3193,"result":"0-1","delta":"+11.6"},{"date":"2022-03-13","black":"Park Hamin","blackElo":3270,"white":"Yun Chanhee","whiteElo":3201,"result":"1-0","delta":"-8.1"},{"date":"2022-03-04","black":"Weon Seongjin","blackElo":3375,"white":"Yun Chanhee","whiteElo":3207,"result":"1-0","delta":"-5.5"},{"date":"2022-03-01","black":"Yun Chanhee","blackElo":3196,"white":"Cho Hanseung","whiteElo":3225,"result":"1-0","delta":"+10.8"},{"date":"2022-02-18","black":"Yun Chanhee","blackElo":3205,"white":"Hong Seongji","whiteElo":3229,"result":"0-1","delta":"-9.3"},{"date":"2022-02-16","black":"Yun Chanhee","blackElo":3212,"white":"Kang Dongyun","whiteElo":3319,"result":"0-1","delta":"-7.0"},{"date":"2022-02-04","black":"Yun Chanhee","blackElo":3220,"white":"Kang Dongyun","whiteElo":3280,"result":"0-1","delta":"-8.3"},{"date":"2022-01-24","black":"Yun Chanhee","blackElo":3228,"white":"Shin Minjun","whiteElo":3323,"result":"0-1","delta":"-7.3"},{"date":"2022-01-21","black":"Yun Chanhee","blackElo":3217,"white":"Lee Wonyoung","whiteElo":3231,"result":"1-0","delta":"+10.4"},{"date":"2022-01-18","black":"Yun Chanhee","blackElo":3230,"white":"Park Seunghwa","whiteElo":3142,"result":"0-1","delta":"-12.5"},{"date":"2022-01-15","black":"Kim Seongjae","blackElo":3186,"white":"Yun Chanhee","whiteElo":3221,"result":"0-1","delta":"+9.0"},{"date":"2022-01-09","black":"Yun Chanhee","blackElo":3228,"white":"Park Yeonghun","whiteElo":3322,"result":"0-1","delta":"-7.4"},{"date":"2021-12-30","black":"Han Sangcho","blackElo":3124,"white":"Yun Chanhee","whiteElo":3221,"result":"0-1","delta":"+7.3"},{"date":"2021-12-27","black":"Baek Hyeonwoo","blackElo":3202,"white":"Yun Chanhee","whiteElo":3211,"result":"0-1","delta":"+9.7"},{"date":"2021-12-25","black":"Yoo Ohseong","blackElo":3045,"white":"Yun Chanhee","whiteElo":3226,"result":"1-0","delta":"-14.8"},{"date":"2021-12-07","black":"Yun Chanhee","blackElo":3235,"white":"Cho Hanseung","whiteElo":3275,"result":"0-1","delta":"-8.8"},{"date":"2021-12-04","black":"Lee Donghoon","blackElo":3385,"white":"Yun Chanhee","whiteElo":3241,"result":"1-0","delta":"-6.1"},{"date":"2021-11-25","black":"Ryu Minhyung","blackElo":3169,"white":"Yun Chanhee","whiteElo":3253,"result":"1-0","delta":"-12.4"},{"date":"2021-11-24","black":"Moon Minjong","blackElo":3221,"white":"Yun Chanhee","whiteElo":3244,"result":"0-1","delta":"+9.4"},{"date":"2021-11-20","black":"Yun Chanhee","blackElo":3236,"white":"Kim Hyeongwoo","whiteElo":3148,"result":"1-0","delta":"+7.5"},{"date":"2021-10-21","black":"Yun Chanhee","blackElo":3245,"white":"Peng Liyao","whiteElo":3293,"result":"0-1","delta":"-8.6"},{"date":"2021-10-18","black":"Han Seungjoo","blackElo":3241,"white":"Yun Chanhee","whiteElo":3235,"result":"0-1","delta":"+10.2"},{"date":"2021-10-04","black":"Kim Myounghoon","blackElo":3292,"white":"Yun Chanhee","whiteElo":3223,"result":"0-1","delta":"+12.0"},{"date":"2021-08-25","black":"Yun Chanhee","blackElo":3212,"white":"Park Hamin","whiteElo":3228,"result":"1-0","delta":"+10.5"},{"date":"2021-08-23","black":"Weon Seongjin","blackElo":3421,"white":"Yun Chanhee","whiteElo":3196,"result":"0-1","delta":"+15.7"},{"date":"2021-07-12","black":"Park Sangjin","blackElo":3219,"white":"Yun Chanhee","whiteElo":3206,"result":"1-0","delta":"-9.6"},{"date":"2021-07-04","black":"An Sungjoon","blackElo":3319,"white":"Yun Chanhee","whiteElo":3213,"result":"1-0","delta":"-7.0"},{"date":"2021-05-16","black":"Kang Dongyun","blackElo":3313,"white":"Yun Chanhee","whiteElo":3221,"result":"1-0","delta":"-7.4"},{"date":"2021-03-16","black":"Yun Chanhee","blackElo":3210,"white":"Park Jaekeun","whiteElo":3240,"result":"1-0","delta":"+10.9"},{"date":"2021-02-25","black":"Park Jinsol","blackElo":3243,"white":"Yun Chanhee","whiteElo":3198,"result":"0-1","delta":"+11.3"},{"date":"2021-01-14","black":"Yun Chanhee","blackElo":3184,"white":"Lee Donghoon","whiteElo":3365,"result":"1-0","delta":"+14.8"},{"date":"2020-11-27","black":"Yun Chanhee","blackElo":3195,"white":"Han Sanghoon","whiteElo":3161,"result":"0-1","delta":"-11.0"},{"date":"2020-11-26","black":"Han Sanghoon","blackElo":3170,"white":"Yun Chanhee","whiteElo":3185,"result":"0-1","delta":"+9.6"},{"date":"2020-11-25","black":"Yun Chanhee","blackElo":3175,"white":"Han Sanghoon","whiteElo":3181,"result":"1-0","delta":"+10.2"},{"date":"2020-11-24","black":"Han Sanghoon","blackElo":3170,"white":"Yun Chanhee","whiteElo":3185,"result":"1-0","delta":"-10.4"},{"date":"2020-11-23","black":"Yun Chanhee","blackElo":3196,"white":"Han Sanghoon","whiteElo":3159,"result":"0-1","delta":"-11.1"},{"date":"2020-11-10","black":"Yun Chanhee","blackElo":3189,"white":"Kim Sonjin","whiteElo":3102,"result":"1-0","delta":"+7.6"},{"date":"2020-11-09","black":"Kim Sonjin","blackElo":3119,"white":"Yun Chanhee","whiteElo":3181,"result":"0-1","delta":"+8.2"},{"date":"2020-10-26","black":"Yun Chanhee","blackElo":3169,"white":"Paek Hongseok","whiteElo":3241,"result":"1-0","delta":"+12.1"},{"date":"2020-10-15","black":"Cho Hyeyeon","blackElo":3120,"white":"Yun Chanhee","whiteElo":3160,"result":"0-1","delta":"+8.9"},{"date":"2020-10-07","black":"Yun Chanhee","blackElo":3152,"white":"On Sojin","whiteElo":3087,"result":"1-0","delta":"+8.2"},{"date":"2020-09-28","black":"Yun Chanhee","blackElo":3160,"white":"Yun Junsang","whiteElo":3223,"result":"0-1","delta":"-8.2"},{"date":"2020-09-17","black":"Kim Sonjin","blackElo":3080,"white":"Yun Chanhee","whiteElo":3172,"result":"1-0","delta":"-12.6"},{"date":"2020-09-10","black":"Yun Chanhee","blackElo":3183,"white":"Park Seunghwa","whiteElo":3173,"result":"0-1","delta":"-10.3"},{"date":"2020-09-02","black":"Han Sanghoon","blackElo":3122,"white":"Yun Chanhee","whiteElo":3174,"result":"0-1","delta":"+8.5"},{"date":"2020-05-19","black":"Yun Chanhee","blackElo":3175,"white":"Shin Jinseo","whiteElo":3650,"result":"0-1","delta":"-1.2"},{"date":"2020-04-13","black":"Yun Chanhee","blackElo":3170,"white":"Kim Yoochan","whiteElo":2973,"result":"1-0","delta":"+4.9"},{"date":"2020-04-08","black":"Yun Chanhee","blackElo":3161,"white":"Song Gyusang","whiteElo":3134,"result":"1-0","delta":"+9.2"},{"date":"2020-01-25","black":"Yun Chanhee","blackElo":3170,"white":"Seol Hyunjun","whiteElo":3227,"result":"0-1","delta":"-8.4"},{"date":"2020-01-17","black":"Yun Chanhee","blackElo":3177,"white":"Paek Hongseok","whiteElo":3262,"result":"0-1","delta":"-7.6"},{"date":"2020-01-16","black":"Lee Jihyun (m)","blackElo":3333,"white":"Yun Chanhee","whiteElo":3163,"result":"0-1","delta":"+14.5"},{"date":"2020-01-02","black":"Han Taehee","blackElo":3191,"white":"Yun Chanhee","whiteElo":3172,"result":"1-0","delta":"-9.5"},{"date":"2019-12-29","black":"Yun Chanhee","blackElo":3162,"white":"Lee Changseok","whiteElo":3156,"result":"1-0","delta":"+9.8"},{"date":"2019-12-21","black":"Kang Dongyun","blackElo":3344,"white":"Yun Chanhee","whiteElo":3168,"result":"1-0","delta":"-5.3"},{"date":"2019-12-18","black":"Yun Chanhee","blackElo":3175,"white":"Kang Seungmin","whiteElo":3261,"result":"0-1","delta":"-7.6"},{"date":"2019-12-12","black":"Park Jonghoon","blackElo":3203,"white":"Yun Chanhee","whiteElo":3164,"result":"0-1","delta":"+11.1"},{"date":"2019-11-29","black":"Yun Chanhee","blackElo":3174,"white":"Ryu Suhang","whiteElo":3176,"result":"0-1","delta":"-9.9"},{"date":"2019-11-22","black":"Seol Hyunjun","blackElo":3213,"white":"Yun Chanhee","whiteElo":3183,"result":"1-0","delta":"-9.1"},{"date":"2019-11-16","black":"Yun Chanhee","blackElo":3191,"white":"Yun Junsang","whiteElo":3264,"result":"0-1","delta":"-7.9"},{"date":"2019-11-03","black":"Yun Chanhee","blackElo":3200,"white":"Kim Myounghoon","whiteElo":3247,"result":"0-1","delta":"-8.6"},{"date":"2019-10-24","black":"Yun Chanhee","blackElo":3191,"white":"Kim Sedong","whiteElo":3141,"result":"1-0","delta":"+8.6"},{"date":"2019-10-18","black":"Yun Chanhee","blackElo":3196,"white":"Shin Minjun","whiteElo":3377,"result":"0-1","delta":"-5.2"},{"date":"2019-10-06","black":"Park Yeonghun","blackElo":3360,"white":"Yun Chanhee","whiteElo":3202,"result":"1-0","delta":"-5.7"},{"date":"2019-09-27","black":"Shin Jinseo","blackElo":3566,"white":"Yun Chanhee","whiteElo":3204,"result":"1-0","delta":"-2.2"},{"date":"2019-07-30","black":"Yun Chanhee","blackElo":3213,"white":"Yun Junsang","whiteElo":3250,"result":"0-1","delta":"-8.9"},{"date":"2019-07-15","black":"Weon Seongjin","blackElo":3301,"white":"Yun Chanhee","whiteElo":3221,"result":"1-0","delta":"-7.7"},{"date":"2019-05-23","black":"Yun Chanhee","blackElo":3225,"white":"Mi Yuting","whiteElo":3460,"result":"0-1","delta":"-4.1"},{"date":"2019-03-19","black":"Han Wonggyu","blackElo":3117,"white":"Yun Chanhee","whiteElo":3218,"result":"0-1","delta":"+7.2"},{"date":"2019-02-17","black":"Yu Zhiying","blackElo":3238,"white":"Yun Chanhee","whiteElo":3207,"result":"0-1","delta":"+10.9"},{"date":"2019-02-16","black":"Yun Chanhee","blackElo":3215,"white":"Zhao Chenyu","whiteElo":3289,"result":"0-1","delta":"-7.9"},{"date":"2018-09-28","black":"Hong Seongji","blackElo":3240,"white":"Yun Chanhee","whiteElo":3224,"result":"1-0","delta":"-9.5"},{"date":"2018-09-21","black":"Yun Chanhee","blackElo":3217,"white":"Hong Kipyo","whiteElo":3132,"result":"1-0","delta":"+7.6"},{"date":"2018-09-14","black":"Shin Minjun","blackElo":3353,"white":"Yun Chanhee","whiteElo":3223,"result":"1-0","delta":"-6.4"},{"date":"2018-09-11","black":"Yun Chanhee","blackElo":3231,"white":"Kim Myounghoon","whiteElo":3321,"result":"0-1","delta":"-7.5"},{"date":"2018-09-01","black":"Ryu Suhang","blackElo":3190,"white":"Yun Chanhee","whiteElo":3242,"result":"1-0","delta":"-11.5"},{"date":"2018-08-26","black":"Yun Chanhee","blackElo":3252,"white":"Park Jinsol","whiteElo":3260,"result":"0-1","delta":"-9.8"},{"date":"2018-08-16","black":"Yun Chanhee","blackElo":3239,"white":"Lee Sedol","whiteElo":3340,"result":"1-0","delta":"+12.8"},{"date":"2018-08-11","black":"Park Yeonghun","blackElo":3347,"white":"Yun Chanhee","whiteElo":3246,"result":"1-0","delta":"-7.2"},{"date":"2018-08-04","black":"Yun Chanhee","blackElo":3237,"white":"Park Minkyu","whiteElo":3223,"result":"1-0","delta":"+9.6"},{"date":"2018-07-21","black":"Kang Seungmin","blackElo":3274,"white":"Yun Chanhee","whiteElo":3225,"result":"0-1","delta":"+11.4"},{"date":"2018-07-17","black":"Shin Jinseo","blackElo":3482,"white":"Yun Chanhee","whiteElo":3229,"result":"1-0","delta":"-3.8"},{"date":"2018-07-14","black":"Yun Chanhee","blackElo":3216,"white":"Kang Dongyun","whiteElo":3325,"result":"1-0","delta":"+13.0"},{"date":"2018-07-12","black":"Cho Hanseung","blackElo":3286,"white":"Yun Chanhee","whiteElo":3204,"result":"0-1","delta":"+12.3"},{"date":"2018-06-29","black":"Choi Jaeyoung","blackElo":3200,"white":"Yun Chanhee","whiteElo":3214,"result":"1-0","delta":"-10.4"},{"date":"2018-06-18","black":"Wang Haoyang","blackElo":3166,"white":"Yun Chanhee","whiteElo":3205,"result":"0-1","delta":"+8.9"},{"date":"2018-06-16","black":"Yun Chanhee","blackElo":3195,"white":"Chen Xian","whiteElo":3201,"result":"1-0","delta":"+10.2"},{"date":"2018-04-02","black":"Yun Chanhee","blackElo":3190,"white":"Jeong Seojun","whiteElo":3010,"result":"1-0","delta":"+5.2"},{"date":"2018-03-09","black":"Kim Jiseok","blackElo":3474,"white":"Yun Chanhee","whiteElo":3193,"result":"1-0","delta":"-3.3"},{"date":"2018-02-02","black":"Hong Seongji","blackElo":3263,"white":"Yun Chanhee","whiteElo":3181,"result":"0-1","delta":"+12.3"},{"date":"2017-12-03","black":"Lee Changho","blackElo":3227,"white":"Yun Chanhee","whiteElo":3190,"result":"1-0","delta":"-8.9"},{"date":"2017-12-02","black":"Yun Chanhee","blackElo":3199,"white":"Lee Changho","whiteElo":3217,"result":"0-1","delta":"-9.5"},{"date":"2017-12-01","black":"Kim Myounghoon","blackElo":3327,"white":"Yun Chanhee","whiteElo":3206,"result":"1-0","delta":"-6.6"},{"date":"2017-11-29","black":"Yun Chanhee","blackElo":3193,"white":"Yun Junsang","whiteElo":3315,"result":"1-0","delta":"+13.4"},{"date":"2017-11-23","black":"Kim Jiseok","blackElo":3428,"white":"Yun Chanhee","whiteElo":3197,"result":"1-0","delta":"-4.2"},{"date":"2017-11-22","black":"Yun Chanhee","blackElo":3204,"white":"Yun Junsang","whiteElo":3296,"result":"0-1","delta":"-7.4"},{"date":"2017-10-26","black":"Yun Junsang","blackElo":3292,"white":"Yun Chanhee","whiteElo":3212,"result":"1-0","delta":"-7.7"},{"date":"2017-10-21","black":"Lee Jihyun (m)","blackElo":3326,"white":"Yun Chanhee","whiteElo":3219,"result":"1-0","delta":"-7.0"},{"date":"2017-10-14","black":"Yun Chanhee","blackElo":3210,"white":"Lee Taehyun","whiteElo":3170,"result":"1-0","delta":"+8.9"},{"date":"2017-10-06","black":"Kim Junghyun","blackElo":3213,"white":"Yun Chanhee","whiteElo":3220,"result":"1-0","delta":"-10.2"},{"date":"2017-10-01","black":"Yun Chanhee","blackElo":3217,"white":"Sim Jaeik","whiteElo":2965,"result":"1-0","delta":"+3.8"},{"date":"2017-09-22","black":"Yun Chanhee","blackElo":3228,"white":"Song Jihoon","whiteElo":3172,"result":"0-1","delta":"-11.6"},{"date":"2017-09-17","black":"Yun Chanhee","blackElo":3232,"white":"Shin Jinseo","whiteElo":3480,"result":"0-1","delta":"-3.9"},{"date":"2017-09-03","black":"Weon Seongjin","blackElo":3313,"white":"Yun Chanhee","whiteElo":3240,"result":"1-0","delta":"-7.9"},{"date":"2017-08-20","black":"Yun Chanhee","blackElo":3229,"white":"Yun Junsang","whiteElo":3279,"result":"1-0","delta":"+11.4"},{"date":"2017-08-11","black":"Jin Siyoung","blackElo":3228,"white":"Yun Chanhee","whiteElo":3218,"result":"0-1","delta":"+10.3"},{"date":"2017-08-04","black":"Yun Chanhee","blackElo":3230,"white":"Lee Taehyun","whiteElo":3170,"result":"0-1","delta":"-11.7"},{"date":"2017-07-22","black":"Yun Chanhee","blackElo":3220,"white":"Kim Junghyun","whiteElo":3232,"result":"1-0","delta":"+10.4"},{"date":"2017-07-13","black":"Lee Sedol","blackElo":3421,"white":"Yun Chanhee","whiteElo":3204,"result":"0-1","delta":"+15.5"},{"date":"2017-07-08","black":"Yun Chanhee","blackElo":3196,"white":"Song Jihoon","whiteElo":3131,"result":"1-0","delta":"+8.2"},{"date":"2017-06-30","black":"Shi Yue","blackElo":3391,"white":"Yun Chanhee","whiteElo":3201,"result":"1-0","delta":"-5.0"},{"date":"2017-06-08","black":"Yun Chanhee","blackElo":3204,"white":"Shin Jinseo","whiteElo":3476,"result":"0-1","delta":"-3.5"},{"date":"2017-06-01","black":"Weon Seongjin","blackElo":3287,"white":"Yun Chanhee","whiteElo":3212,"result":"1-0","delta":"-7.9"},{"date":"2017-03-09","black":"Yun Chanhee","blackElo":3223,"white":"Heo Yongho","whiteElo":3211,"result":"0-1","delta":"-10.3"},{"date":"2016-12-11","black":"Yun Chanhee","blackElo":3231,"white":"Kang Yootaek","whiteElo":3288,"result":"0-1","delta":"-8.4"},{"date":"2016-12-03","black":"Yun Chanhee","blackElo":3222,"white":"Park Minkyu","whiteElo":3197,"result":"1-0","delta":"+9.3"},{"date":"2016-12-02","black":"Yun Chanhee","blackElo":3233,"white":"Kim Seongjae","whiteElo":3194,"result":"0-1","delta":"-11.1"},{"date":"2016-10-23","black":"Yun Chanhee","blackElo":3244,"white":"Kim Seongjae","whiteElo":3202,"result":"0-1","delta":"-11.2"},{"date":"2016-10-16","black":"Yun Chanhee","blackElo":3234,"white":"Han Taehee","whiteElo":3222,"result":"1-0","delta":"+9.6"},{"date":"2016-09-29","black":"Park Yeonghun","blackElo":3369,"white":"Yun Chanhee","whiteElo":3241,"result":"1-0","delta":"-6.5"},{"date":"2016-09-23","black":"Park Cheongsang","blackElo":3181,"white":"Yun Chanhee","whiteElo":3232,"result":"0-1","delta":"+8.5"},{"date":"2016-09-17","black":"Yun Chanhee","blackElo":3223,"white":"Lee Hobum","whiteElo":3192,"result":"1-0","delta":"+9.1"},{"date":"2016-09-04","black":"Lee Jihyun (m)","blackElo":3287,"white":"Yun Chanhee","whiteElo":3211,"result":"0-1","delta":"+12.1"},{"date":"2016-08-27","black":"Hong Kipyo","blackElo":3108,"white":"Yun Chanhee","whiteElo":3204,"result":"0-1","delta":"+7.3"},{"date":"2016-08-20","black":"Yun Chanhee","blackElo":3212,"white":"Yun Junsang","whiteElo":3268,"result":"0-1","delta":"-8.4"},{"date":"2016-08-11","black":"Yun Chanhee","blackElo":3206,"white":"Kim Sooyong","whiteElo":3052,"result":"1-0","delta":"+5.8"},{"date":"2016-07-28","black":"Yun Chanhee","blackElo":3215,"white":"Paek Hongseok","whiteElo":3263,"result":"0-1","delta":"-8.6"},{"date":"2016-07-10","black":"Yun Chanhee","blackElo":3229,"white":"Kang Seungmin","whiteElo":3088,"result":"0-1","delta":"-13.9"},{"date":"2016-06-25","black":"Hong Seongji","blackElo":3309,"white":"Yun Chanhee","whiteElo":3237,"result":"1-0","delta":"-8.0"},{"date":"2016-06-17","black":"Yun Chanhee","blackElo":3228,"white":"Lee Hobum","whiteElo":3184,"result":"1-0","delta":"+8.7"},{"date":"2016-06-13","black":"Kim Seungjun","blackElo":3101,"white":"Yun Chanhee","whiteElo":3242,"result":"1-0","delta":"-13.8"},{"date":"2016-06-09","black":"Yun Chanhee","blackElo":3248,"white":"Kang Dongyun","whiteElo":3374,"result":"0-1","delta":"-6.5"},{"date":"2016-06-03","black":"Shin Jinseo","blackElo":3388,"white":"Yun Chanhee","whiteElo":3255,"result":"1-0","delta":"-6.4"},{"date":"2016-05-20","black":"Kim Jiseok","blackElo":3423,"white":"Yun Chanhee","whiteElo":3260,"result":"1-0","delta":"-5.6"},{"date":"2016-04-28","black":"Yun Chanhee","blackElo":3267,"white":"Lee Donghoon","whiteElo":3381,"result":"0-1","delta":"-6.8"},{"date":"2016-04-15","black":"Lee Donghoon","blackElo":3378,"white":"Yun Chanhee","whiteElo":3274,"result":"1-0","delta":"-7.1"},{"date":"2016-04-14","black":"Yun Chanhee","blackElo":3282,"white":"Lee Donghoon","whiteElo":3370,"result":"0-1","delta":"-7.5"},{"date":"2016-04-07","black":"Yun Chanhee","blackElo":3270,"white":"Weon Seongjin","whiteElo":3330,"result":"1-0","delta":"+11.7"},{"date":"2016-03-24","black":"Yun Chanhee","blackElo":3258,"white":"Shin Jinseo","whiteElo":3350,"result":"1-0","delta":"+12.6"},{"date":"2016-03-21","black":"Park Yeonghun","blackElo":3409,"white":"Yun Chanhee","whiteElo":3228,"result":"0-1","delta":"+29.6"},{"date":"2016-02-14","black":"Yun Chanhee","blackElo":3204,"white":"Kim Myounghoon","whiteElo":3278,"result":"1-0","delta":"+24.2"},{"date":"2016-01-14","black":"Yun Chanhee","blackElo":3187,"white":"Kang Seungmin","whiteElo":3125,"result":"1-0","delta":"+16.5"},{"date":"2015-10-14","black":"Yun Chanhee","blackElo":3219,"white":"Park Jaekeun","whiteElo":2974,"result":"0-1","delta":"-32.2"},{"date":"2015-10-09","black":"Yun Chanhee","blackElo":3210,"white":"Kim Hyemin","whiteElo":3008,"result":"1-0","delta":"+9.5"},{"date":"2015-09-30","black":"Yun Chanhee","blackElo":3200,"white":"Choi Myeonghun","whiteElo":3016,"result":"1-0","delta":"+10.3"},{"date":"2015-09-26","black":"Yun Chanhee","blackElo":3190,"white":"Kim Hwansoo","whiteElo":2980,"result":"1-0","delta":"+9.2"},{"date":"2015-09-23","black":"Hwang Jaeyeon","blackElo":3074,"white":"Yun Chanhee","whiteElo":3218,"result":"1-0","delta":"-27.8"},{"date":"2015-09-20","black":"Yun Chanhee","blackElo":3244,"white":"Kang Seungmin","whiteElo":3145,"result":"0-1","delta":"-25.5"},{"date":"2015-09-05","black":"Yun Chanhee","blackElo":3225,"white":"Ryu Suhang","whiteElo":3201,"result":"1-0","delta":"+18.6"},{"date":"2015-09-02","black":"Min Sangyoun","blackElo":3180,"white":"Yun Chanhee","whiteElo":3249,"result":"1-0","delta":"-23.9"},{"date":"2015-08-22","black":"Yun Chanhee","blackElo":3246,"white":"Lee Yongchan","whiteElo":2826,"result":"1-0","delta":"+3.3"},{"date":"2015-08-16","black":"Shin Yoonho","blackElo":3059,"white":"Yun Chanhee","whiteElo":3235,"result":"0-1","delta":"+10.7"},{"date":"2015-07-25","black":"Lee Changseok","blackElo":3021,"white":"Yun Chanhee","whiteElo":3226,"result":"0-1","delta":"+9.4"},{"date":"2015-07-18","black":"Choi Jaeyoung","blackElo":3016,"white":"Yun Chanhee","whiteElo":3216,"result":"0-1","delta":"+9.6"},{"date":"2015-07-17","black":"Mok Jinseok","blackElo":3248,"white":"Yun Chanhee","whiteElo":3235,"result":"1-0","delta":"-19.3"},{"date":"2015-07-05","black":"Kim Hyemin","blackElo":3020,"white":"Yun Chanhee","whiteElo":3226,"result":"0-1","delta":"+9.4"},{"date":"2015-07-01","black":"You Byungyong","blackElo":2990,"white":"Yun Chanhee","whiteElo":3259,"result":"1-0","delta":"-33.0"},{"date":"2015-06-20","black":"Park Jaekeun","blackElo":3039,"white":"Yun Chanhee","whiteElo":3250,"result":"0-1","delta":"+9.2"},{"date":"2015-06-18","black":"Park Jaekeun","blackElo":3006,"white":"Yun Chanhee","whiteElo":3283,"result":"1-0","delta":"-33.3"},{"date":"2015-06-17","black":"Yun Chanhee","blackElo":3269,"white":"Ryu Suhang","whiteElo":3161,"result":"1-0","delta":"+14.0"},{"date":"2015-06-14","black":"Yun Chanhee","blackElo":3255,"white":"Lee Taehyun","whiteElo":3153,"result":"1-0","delta":"+14.3"},{"date":"2015-05-17","black":"Park Jinsol","blackElo":3115,"white":"Yun Chanhee","whiteElo":3284,"result":"1-0","delta":"-29.0"},{"date":"2015-05-16","black":"Yun Chanhee","blackElo":3267,"white":"Min Sangyoun","whiteElo":3221,"result":"1-0","delta":"+17.4"},{"date":"2015-05-09","black":"Yun Chanhee","blackElo":3258,"white":"Park Hamin","whiteElo":3037,"result":"1-0","delta":"+8.8"},{"date":"2015-05-03","black":"Yun Chanhee","blackElo":3247,"white":"Ko Keuntae","whiteElo":3082,"result":"1-0","delta":"+11.2"},{"date":"2015-04-26","black":"Kim Juho","blackElo":3189,"white":"Yun Chanhee","whiteElo":3271,"result":"1-0","delta":"-24.7"},{"date":"2015-02-02","black":"Lee Donghoon","blackElo":3291,"white":"Yun Chanhee","whiteElo":3291,"result":"1-0","delta":"-20.0"},{"date":"2015-01-19","black":"An Sungjoon","blackElo":3220,"white":"Yun Chanhee","whiteElo":3274,"result":"0-1","delta":"+16.9"},{"date":"2015-01-16","black":"Kim Junghyun","blackElo":3292,"white":"Yun Chanhee","whiteElo":3252,"result":"0-1","delta":"+22.3"},{"date":"2014-12-22","black":"Kim Jiseok","blackElo":3446,"white":"Yun Chanhee","whiteElo":3221,"result":"0-1","delta":"+31.4"},{"date":"2014-11-04","black":"Yun Chanhee","blackElo":3213,"white":"Yang Wooseok","whiteElo":2955,"result":"1-0","delta":"+7.4"},{"date":"2014-10-27","black":"Yun Chanhee","blackElo":3225,"white":"Kang Dongyun","whiteElo":3381,"result":"0-1","delta":"-11.6"},{"date":"2014-10-26","black":"Ko Keuntae","blackElo":3108,"white":"Yun Chanhee","whiteElo":3211,"result":"0-1","delta":"+14.3"},{"date":"2014-10-20","black":"Yun Chanhee","blackElo":3188,"white":"Min Sangyoun","whiteElo":3235,"result":"1-0","delta":"+22.7"},{"date":"2014-10-11","black":"Yun Chanhee","blackElo":3178,"white":"Seol Hyunjun","whiteElo":2993,"result":"1-0","delta":"+10.3"},{"date":"2014-10-09","black":"Lee Jihyun (m)","blackElo":3247,"white":"Yun Chanhee","whiteElo":3195,"result":"1-0","delta":"-17.0"},{"date":"2014-10-06","black":"Yun Chanhee","blackElo":3213,"white":"Lee Donghoon","whiteElo":3238,"result":"0-1","delta":"-18.5"},{"date":"2014-09-26","black":"Yun Chanhee","blackElo":3201,"white":"Kim Hyeongwoo","whiteElo":3066,"result":"1-0","delta":"+12.6"},{"date":"2014-09-21","black":"Yun Chanhee","blackElo":3191,"white":"Song Sanghun","whiteElo":2990,"result":"1-0","delta":"+9.6"},{"date":"2014-09-18","black":"Yun Chanhee","blackElo":3172,"white":"Lee Taehyun","whiteElo":3153,"result":"1-0","delta":"+18.9"},{"date":"2014-09-07","black":"Yun Chanhee","blackElo":3160,"white":"Choi Hyunjae","whiteElo":3017,"result":"1-0","delta":"+12.2"},{"date":"2014-08-16","black":"Yun Chanhee","blackElo":3138,"white":"Park Changmyeong","whiteElo":3177,"result":"1-0","delta":"+22.3"},{"date":"2014-08-09","black":"Yun Chanhee","blackElo":3167,"white":"Cho Insun","whiteElo":2993,"result":"0-1","delta":"-29.2"},{"date":"2014-07-15","black":"Kim Daeyoung","blackElo":2999,"white":"Yun Chanhee","whiteElo":3155,"result":"0-1","delta":"+11.6"},{"date":"2014-07-12","black":"Yun Chanhee","blackElo":3178,"white":"Park Jinsol","whiteElo":3126,"result":"0-1","delta":"-23.0"},{"date":"2014-06-28","black":"Lee Hyungjin","blackElo":3088,"white":"Yun Chanhee","whiteElo":3205,"result":"1-0","delta":"-26.5"},{"date":"2014-06-26","black":"Yun Chanhee","blackElo":3234,"white":"Lee Hyungjin","whiteElo":3059,"result":"0-1","delta":"-29.3"},{"date":"2014-06-15","black":"Kang Seungmin","blackElo":3017,"white":"Yun Chanhee","whiteElo":3225,"result":"0-1","delta":"+9.3"},{"date":"2014-06-07","black":"Kim Hyeongwoo","blackElo":3078,"white":"Yun Chanhee","whiteElo":3212,"result":"0-1","delta":"+12.7"},{"date":"2014-05-24","black":"Yun Chanhee","blackElo":3203,"white":"Park Daeyoung","whiteElo":2998,"result":"1-0","delta":"+9.4"},{"date":"2014-05-11","black":"Park Changmyeong","blackElo":3066,"white":"Yun Chanhee","whiteElo":3190,"result":"0-1","delta":"+13.2"},{"date":"2014-04-13","black":"Yun Chanhee","blackElo":3217,"white":"Hong Kipyo","whiteElo":3084,"result":"0-1","delta":"-27.3"},{"date":"2014-02-17","black":"Na Hyun","blackElo":3271,"white":"Yun Chanhee","whiteElo":3192,"result":"0-1","delta":"+24.5"},{"date":"2011-09-30","black":"Mok Jinseok","blackElo":3278,"white":"Yun Chanhee","whiteElo":3208,"result":"1-0","delta":"-16.1"},{"date":"2011-09-27","black":"Yun Chanhee","blackElo":3221,"white":"Lee Changho","whiteElo":3362,"result":"0-1","delta":"-12.3"},{"date":"2011-08-09","black":"Yang Keon","blackElo":3009,"white":"Yun Chanhee","whiteElo":3211,"result":"0-1","delta":"+9.5"},{"date":"2011-07-08","black":"Yun Chanhee","blackElo":3223,"white":"Park Yeonghun","whiteElo":3378,"result":"0-1","delta":"-11.6"},{"date":"2011-01-17","black":"Kim Juho","blackElo":3140,"white":"Yun Chanhee","whiteElo":3249,"result":"1-0","delta":"-26.1"},{"date":"2010-10-06","black":"An Joyeong","blackElo":3241,"white":"Yun Chanhee","whiteElo":3271,"result":"1-0","delta":"-21.7"},{"date":"2010-07-22","black":"Park Junghwan","blackElo":3393,"white":"Yun Chanhee","whiteElo":3242,"result":"0-1","delta":"+28.2"},{"date":"2010-04-20","black":"Yun Chanhee","blackElo":3217,"white":"Zhou Heyang","whiteElo":3319,"result":"1-0","delta":"+25.7"},{"date":"2010-01-18","black":"Lee Changho","blackElo":3380,"white":"Yun Chanhee","whiteElo":3229,"result":"1-0","delta":"-11.8"},{"date":"2009-12-14","black":"Yun Chanhee","blackElo":3206,"white":"An Joyeong","whiteElo":3254,"result":"1-0","delta":"+22.7"},{"date":"2009-11-23","black":"Lee Huiseong","blackElo":3142,"white":"Yun Chanhee","whiteElo":3188,"result":"0-1","delta":"+17.3"},{"date":"2009-11-09","black":"Yun Chanhee","blackElo":3171,"white":"Han Sanghoon","whiteElo":3134,"result":"1-0","delta":"+17.9"},{"date":"2009-08-17","black":"Yun Chanhee","blackElo":3157,"white":"Kang Changbae","whiteElo":3034,"result":"1-0","delta":"+13.2"},{"date":"2009-06-01","black":"Yun Chanhee","blackElo":3165,"white":"Kang Dongyun","whiteElo":3416,"result":"0-1","delta":"-7.6"},{"date":"2009-03-23","black":"Jen Youngkyu","blackElo":3001,"white":"Yun Chanhee","whiteElo":3153,"result":"0-1","delta":"+11.7"},{"date":"2008-12-13","black":"Heo Yongho","blackElo":3287,"white":"Yun Chanhee","whiteElo":3167,"result":"1-0","delta":"-13.3"},{"date":"2008-12-06","black":"Yun Chanhee","blackElo":3140,"white":"Kang Yootaek","whiteElo":3252,"result":"1-0","delta":"+26.2"},{"date":"2008-10-30","black":"Lee Sedol","blackElo":3421,"white":"Yun Chanhee","whiteElo":3147,"result":"1-0","delta":"-6.9"},{"date":"2008-10-24","black":"Bae Junhee","blackElo":3097,"white":"Yun Chanhee","whiteElo":3129,"result":"0-1","delta":"+18.2"},{"date":"2008-10-13","black":"Yun Chanhee","blackElo":3105,"white":"Hong Minpyo","whiteElo":3171,"result":"1-0","delta":"+23.8"},{"date":"2008-10-12","black":"Yun Chanhee","blackElo":3087,"white":"Kim Dongyeop","whiteElo":3053,"result":"1-0","delta":"+18.0"},{"date":"2008-09-20","black":"Yun Chanhee","blackElo":3104,"white":"Cho Hunhyun","whiteElo":3166,"result":"0-1","delta":"-16.5"},{"date":"2008-09-10","black":"Yun Chanhee","blackElo":3072,"white":"Han Sanghoon","whiteElo":3305,"result":"1-0","delta":"+31.7"},{"date":"2008-08-08","black":"Cho Hanseung","blackElo":3275,"white":"Yun Chanhee","whiteElo":3082,"result":"1-0","delta":"-9.9"},{"date":"2008-07-25","black":"Yun Chanhee","blackElo":3057,"white":"On Sojin","whiteElo":3152,"result":"1-0","delta":"+25.3"},{"date":"2008-06-11","black":"Yun Chanhee","blackElo":3065,"white":"Mok Jinseok","whiteElo":3288,"result":"0-1","delta":"-8.7"},{"date":"2008-06-10","black":"Mok Jinseok","blackElo":3284,"white":"Yun Chanhee","whiteElo":3075,"result":"1-0","delta":"-9.2"},{"date":"2008-05-09","black":"Cho Hyeyeon","blackElo":3108,"white":"Yun Chanhee","whiteElo":3094,"result":"1-0","delta":"-19.2"},{"date":"2008-05-07","black":"Yun Chanhee","blackElo":3074,"white":"Lee Seongjae","whiteElo":3069,"result":"1-0","delta":"+19.7"},{"date":"2008-05-06","black":"Lee Yeonggu","blackElo":3281,"white":"Yun Chanhee","whiteElo":3084,"result":"1-0","delta":"-9.7"},{"date":"2008-05-02","black":"Yun Chanhee","blackElo":3096,"white":"An Joyeong","whiteElo":3248,"result":"0-1","delta":"-11.7"},{"date":"2008-04-18","black":"Yun Chanhee","blackElo":3111,"white":"Kim Juho","whiteElo":3191,"result":"0-1","delta":"-15.5"},{"date":"2008-04-11","black":"Lee Jungwoo","blackElo":3142,"white":"Yun Chanhee","whiteElo":3088,"result":"0-1","delta":"+23.1"},{"date":"2008-02-01","black":"Yun Chanhee","blackElo":3104,"white":"Han Sanghoon","whiteElo":3174,"result":"0-1","delta":"-16.0"},{"date":"2007-12-21","black":"Hong Minpyo","blackElo":3216,"white":"Yun Chanhee","whiteElo":3119,"result":"1-0","delta":"-14.5"},{"date":"2007-11-17","black":"Yun Chanhee","blackElo":3083,"white":"Lee Sedol","whiteElo":3453,"result":"1-0","delta":"+35.8"},{"date":"2007-10-21","black":"Kim Kiyoung","blackElo":3126,"white":"Yun Chanhee","whiteElo":3101,"result":"1-0","delta":"-18.6"},{"date":"2007-09-13","black":"Yun Chanhee","blackElo":3073,"white":"Heo Yongho","whiteElo":3231,"result":"1-0","delta":"+28.5"},{"date":"2007-07-22","black":"Park Cheongsang","blackElo":3266,"white":"Yun Chanhee","whiteElo":3041,"result":"0-1","delta":"+31.4"},{"date":"2007-07-16","black":"Yun Chanhee","blackElo":3053,"white":"Kim Jiseok","whiteElo":3207,"result":"0-1","delta":"-11.7"},{"date":"2007-07-13","black":"Kim Hyemin","blackElo":2979,"white":"Yun Chanhee","whiteElo":3036,"result":"0-1","delta":"+16.7"},{"date":"2007-06-14","black":"Yun Chanhee","blackElo":3047,"white":"Heo Yongho","whiteElo":3228,"result":"0-1","delta":"-10.4"},{"date":"2007-05-12","black":"Yun Chanhee","blackElo":3018,"white":"Cho Hunhyun","whiteElo":3190,"result":"1-0","delta":"+29.2"},{"date":"2007-05-06","black":"Yun Chanhee","blackElo":3024,"white":"Paek Hongseok","whiteElo":3299,"result":"0-1","delta":"-6.8"},{"date":"2007-04-06","black":"Yun Chanhee","blackElo":3033,"white":"Yun Junsang","whiteElo":3262,"result":"0-1","delta":"-8.4"},{"date":"2007-04-04","black":"Mok Jinseok","blackElo":3267,"white":"Yun Chanhee","whiteElo":3000,"result":"0-1","delta":"+32.9"}]
